Workbook

Sheet PPS
K1: =SUBTOTAL(9,K3:K1048576) -> 36421 | M1: =SUBTOTAL(9,M3:M1048576) -> 2.0191388e+09
A2: Год | B2: Месяц | C2: Дата | D2: Номер СФ | E2: Медпредставитель | F2: Команда | G2: РМ | H2: Поставщик | I2: Название организации | J2: Наименование | K2: Количество | L2: Цена | M2: Сумма | N2: % наценки | O2: Сумма наценки
A3: 2025 | B3: 3 | C3: 45730 | D3: PPS00002118 | E3: Сарварбек ака | F3: Сурхондарьё_Сарвар ака | G3: Азизбек ака | H3: PPS | I3: "Nurbek Layt" Xk | J3: Эльфор р-р. для инф 5м/мл | K3: 40 | L3: 36955.08 | M3: 1478203.2 | N3: 8 | O3: 118256.26
A4: 2025 | B4: 3 | C4: 45743 | D4: PPS00002496 | E4: Нозими опа (Бух) | F4: Бухоро_Рустам ака | G4: Зикрулло ака | H4: PPS | I4: "Diabetes Pharma" Mchj | J4: Эльфор р-р. для инф 5м/мл | K4: 120 | L4: 36955.08 | M4: 4434609.6 | N4: 8 | O4: 354768.77
A5: 2025 | B5: 4 | C5: 45750 | D5: PPS00002647 | E5: Нозими опа (Бух) | F5: Бухоро_Рустам ака | G5: Зикрулло ака | H5: PPS | I5: "IBN SINO" XK | J5: Эльфор р-р. для инф 5м/мл | K5: 30 | L5: 36955.08 | M5: 1108652.4 | N5: 13 | O5: 144124.81
A6: 2025 | B6: 4 | C6: 45751 | D6: PPS00002691 | E6: Рустам ака (Т.О) | F6: Таш,Обл_Рустам ака | G6: Козим ака | H6: PPS | I6: "Farma Com Pro" Mchj | J6: Эльфор р-р. для инф 5м/мл | K6: 20 | L6: 36955.08 | M6: 739101.6 | N6: 15 | O6: 110865.24
A7: 2025 | B7: 4 | C7: 45772 | D7: PPS00003424 | E7: Сарварбек ака | F7: Сурхондарьё_Сарвар ака | G7: Азизбек ака | H7: PPS | I7: Sport Plyus Xk | J7: Эльфор р-р. для инф 5м/мл | K7: 20 | L7: 36955.08 | M7: 739101.6 | N7: 14 | O7: 103474.22
A8: 2025 | B8: 4 | C8: 45776 | D8: PPS00003544 | E8: Хуршид Ака 3 (Сам) | F8: Самарканд_Хуршед ака | G8: Алишер | H8: PPS | I8: "Star Asadbek" Mchj | J8: Эльфор р-р. для инф 5м/мл | K8: 100 | L8: 36955.08 | M8: 3695508 | N8: 15 | O8: 554326.2
A9: 2025 | B9: 4 | C9: 45776 | D9: PPS00003551 | E9: Сарварбек ака | F9: Сурхондарьё_Сарвар ака | G9: Азизбек ака | H9: PPS | I9: "Nurbek Layt" Xk | J9: Эльфор р-р. для инф 5м/мл | K9: 50 | L9: 36955.08 | M9: 1847754 | N9: 8 | O9: 147820.32
A10: 2025 | B10: 5 | C10: 45779 | D10: PPS00003627 | E10: Рустам ака (Т.О) | F10: Таш,Обл_Рустам ака | G10: Козим ака | H10: PPS | I10: "Farma Com Pro" Mchj | J10: Эльфор р-р. для инф 5м/мл | K10: 42 | L10: 36955.08 | M10: 1552113.4 | N10: 10 | O10: 155211.34
A11: 2025 | B11: 5 | C11: 45783 | D11: PPS00003759 | E11: Нозими опа (Бух) | F11: Бухоро_Рустам ака | G11: Зикрулло ака | H11: PPS | I11: "Buxoro Dori Darmon" Mchj | J11: Эльфор р-р. для инф 5м/мл | K11: 1500 | L11: 36955.08 | M11: 55432620 | N11: 8 | O11: 4434609.6
A12: 2025 | B12: 5 | C12: 45783 | D12: PPS00003759 | E12: Нозими опа (Бух) | F12: Бухоро_Рустам ака | G12: Зикрулло ака | H12: PPS | I12: "Buxoro Dori Darmon" Mchj | J12: Эльфор р-р. для инф 5м/мл | K12: 1500 | L12: 36955.08 | M12: 55432620 | N12: 8 | O12: 4434609.6
A13: 2025 | B13: 5 | C13: 45805 | D13: PPS00004467 | E13: Абдушукур ака (Сир) | F13: Сирдарё_Фотима опа | G13: Алишер | H13: PPS | I13: ЧП "Aju-Biznes-Star" | J13: Эльфор р-р. для инф 5м/мл | K13: 40 | L13: 36955.08 | M13: 1478203.2 | N13: 13 | O13: 192166.42
A14: 2025 | B14: 6 | C14: 45812 | D14: PPS00004665 | E14: Фотима опа (Сир) | F14: Сирдарё_Фотима опа | G14: Алишер | H14: PPS | I14: MCHJ Asad Jahongir Farm | J14: Эльфор р-р. для инф 5м/мл | K14: 500 | L14: 36955.08 | M14: 18477540 | N14: 15 | O14: 2771631
... A624: 2026 | B624: 5 | C624: 46157 | D624: PPS00004515 | E624: Анвар ака (Срд) | F624: Сурхондарьё_Анвар ака | G624: Алишер | H624: PPS | I624: "Sariosiyo Xusan Farm" Xk | J624: Эпсол раствор для инфузий 12 мг/мл 50 мл | K624: 18 | L624: 65000 | M624: 1170000 | N624: 15 | O624: 175500

Sheet IPS
K1: =SUBTOTAL(9,K3:K1048576) -> 11777 | M1: =SUBTOTAL(9,M3:M1048576) -> 7.1832483e+08
A2: Год | B2: Месяц | C2: Дата | D2: Номер СФ | E2: Медпредставитель | F2: Команда | G2: РМ | H2: Поставщик | I2: Название организации | J2: Наименование | K2: Количество | L2: Цена | M2: Сумма | N2: % наценки | O2: Сумма наценки
A3: 2025 | B3: 3 | C3: 45721 | D3: GB000000662 | E3: Фотима опа | F3: Сирдарьё_Фотима Опа | G3: Козим ака | H3: GB | I3: "Ozodbek-Yan-Farm" Xk | J3: Эльфор р-р. для инф 5м/мл | K3: 20 | L3: 36955.08 | M3: 739101.6 | N3: 15 | O3: 110865.24
A4: 2025 | B4: 3 | C4: 45728 | D4: GB000000733 | E4: Фотима опа | F4: Сирдарьё_Фотима Опа | G4: Козим ака | H4: GB | I4: "Behzod-Farm-Yangiyer" Mchj | J4: Эльфор р-р. для инф 5м/мл | K4: 30 | L4: 36955.08 | M4: 1108652.4 | N4: 15 | O4: 166297.86
A5: 2025 | B5: 3 | C5: 45733 | D5: GB000000770 | E5: Фотима опа | F5: Сирдарьё_Фотима Опа | G5: Козим ака | H5: GB | I5: "Baxtiyor Turg'unovich" Ktxf | J5: Эльфор р-р. для инф 5м/мл | K5: 60 | L5: 36955.08 | M5: 2217304.8 | N5: 15 | O5: 332595.72
A6: 2025 | B6: 3 | C6: 45733 | D6: GB000000776 | E6: Фотима опа | F6: Сирдарьё_Фотима Опа | G6: Козим ака | H6: GB | I6: "Ozodbek-Yan-Farm" Xk | J6: Эльфор р-р. для инф 5м/мл | K6: 50 | L6: 36955.08 | M6: 1847754 | N6: 15 | O6: 277163.1
A7: 2025 | B7: 4 | C7: 45749 | D7: GB000000922 | E7: Фотима опа | F7: Сирдарьё_Фотима Опа | G7: Козим ака | H7: GB | I7: Asad Jahongir Farm Mchj | J7: Эльфор р-р. для инф 5м/мл | K7: 43 | L7: 36955.08 | M7: 1589068.4 | N7: 15 | O7: 238360.27
A8: 2025 | B8: 4 | C8: 45751 | D8: GB000000954 | E8: Фотима опа | F8: Сирдарьё_Фотима Опа | G8: Козим ака | H8: GB | I8: "Askarbinka Vitaminka" Mchj | J8: Эльфор р-р. для инф 5м/мл | K8: 50 | L8: 36955.08 | M8: 1847754 | N8: 15 | O8: 277163.1
A9: 2025 | B9: 5 | C9: 45798 | D9: GB000001499 | F9: Тошкент_0 | G9: Козим ака | H9: GB | I9: "Profi Pharm Service" Mchj | J9: Эльфор р-р. для инф 5м/мл | K9: 3827 | L9: 36955.08 | M9: 1.4142709e+08 | N9: 3 | O9: 4242812.7
A10: 2026 | B10: 1 | C10: 46035 | D10: GB000000070 | E10: Дилнавоз опа (Тош) | F10: Ташкент_Дилнавоз опа | G10: Козим ака | H10: GB | I10: "CITY PHARM" mas'uliyati cheklangan jamiyati | J10: Эпсол раствор для инфузий 12 мг/мл 50 мл | K10: 10 | L10: 65000 | M10: 650000 | N10: 5 | O10: 32500
A11: 2026 | B11: 1 | C11: 46036 | D11: GB000000085 | E11: Дилнавоз опа (Тош) | F11: Ташкент_Дилнавоз опа | G11: Козим ака | H11: GB | I11: "Apteka Klassika" Mchj | J11: Миранол раствор для инфузий 50 мл | K11: 40 | L11: 90000 | M11: 3600000 | N11: 5 | O11: 180000
A12: 2026 | B12: 1 | C12: 46036 | D12: GB000000085 | E12: Дилнавоз опа (Тош) | F12: Ташкент_Дилнавоз опа | G12: Козим ака | H12: GB | I12: "Apteka Klassika" Mchj | J12: Эпсол раствор для инфузий 12 мг/мл 50 мл | K12: 20 | L12: 65000 | M12: 1300000 | N12: 5 | O12: 65000
A13: 2026 | B13: 1 | C13: 46036 | D13: GB000000092 | E13: Мехриддин ака (Нав) | F13: Навоий_Мехриддин ака | G13: Козим ака | H13: GB | I13: "Jaxon-Farm-Javohir" Mchj | J13: Ландиос Раствор для инфузий 100мл стеклянные флаконы | K13: 20 | L13: 64700 | M13: 1294000 | N13: 10 | O13: 129400
A14: 2026 | B14: 1 | C14: 46037 | D14: GB000000099 | E14: Дилором опа (Тош) | F14: Ташкент_Дилнавоз опа | G14: Козим ака | H14: GB | I14: "Health Planeta" Mchj | J14: Ландиос Раствор для инфузий 100мл стеклянные флаконы | K14: 10 | L14: 64700 | M14: 647000 | N14: 5 | O14: 32350
A15: 2026 | B15: 1 | C15: 46037 | D15: GB000000099 | E15: Дилором опа (Тош) | F15: Ташкент_Дилнавоз опа | G15: Козим ака | H15: GB | I15: "Health Planeta" Mchj | J15: Эпсол раствор для инфузий 12 мг/мл 50 мл | K15: 20 | L15: 65000 | M15: 1300000 | N15: 5 | O15: 65000
A16: 2026 | B16: 1 | C16: 46037 | D16: GB000000100 | E16: Дилнавоз опа (Тош) | F16: Ташкент_Дилнавоз опа | G16: Козим ака | H16: GB | I16: "Prosperiti-Farm" Mchj | J16: Миранол раствор для инфузий 50 мл | K16: 10 | L16: 90000 | M16: 900000 | N16: 5 | O16: 45000
A17: 2026 | B17: 1 | C17: 46037 | D17: GB000000103 | E17: Дилором опа (Тош) | F17: Ташкент_Дилнавоз опа | G17: Козим ака | H17: GB | I17: "Farhod Buyuk Farm" Mchj | J17: Эпсол раствор для инфузий 12 мг/мл 50 мл | K17: 50 | L17: 65000 | M17: 3250000 | N17: 5 | O17: 162500
A18: 2026 | B18: 1 | C18: 46038 | D18: GB000000108 | E18: Дилором опа (Тош) | F18: Ташкент_Дилнавоз опа | G18: Козим ака | H18: GB | I18: "Shifo-Pharm 111" Mchj | J18: Эпсол раствор для инфузий 12 мг/мл 50 мл | K18: 32 | L18: 65000 | M18: 2080000 | N18: 5 | O18: 104000
A19: 2026 | B19: 1 | C19: 46038 | D19: GB000000108 | E19: Дилором опа (Тош) | F19: Ташкент_Дилнавоз опа | G19: Козим ака | H19: GB | I19: "Shifo-Pharm 111" Mchj | J19: Ландиос Раствор для инфузий 100мл стеклянные флаконы | K19: 20 | L19: 64700 | M19: 1294000 | N19: 5 | O19: 64700
A20: 2026 | B20: 1 | C20: 46038 | D20: GB000000122 | F20: Ташкент_Дилнавоз опа | G20: Козим ака | H20: GB | I20: "Umar Fayz Farm" Mchj | J20: Эпсол раствор для инфузий 12 мг/мл 50 мл | K20: 10 | L20: 65000 | M20: 650000 | N20: 5 | O20: 32500
A21: 2026 | B21: 1 | C21: 46038 | D21: GB000000122 | F21: Ташкент_Дилнавоз опа | G21: Козим ака | H21: GB | I21: "Umar Fayz Farm" Mchj | J21: Миранол раствор для инфузий 50 мл | K21: 10 | L21: 90000 | M21: 900000 | N21: 5 | O21: 45000
A22: 2026 | B22: 1 | C22: 46041 | D22: GB000000125 | E22: Нигора (Тош) | F22: Ташкент_Дилнавоз опа | G22: Козим ака | H22: GB | I22: World Of Medicine Mchj | J22: Эпсол раствор для инфузий 12 мг/мл 50 мл | K22: 50 | L22: 65000 | M22: 3250000 | N22: 5 | O22: 162500
A23: 2026 | B23: 1 | C23: 46041 | D23: GB000000127 | E23: Мехриддин ака (Нав) | F23: Навоий_Мехриддин ака | G23: Козим ака | H23: GB | I23: "Vita Pharm Navoiy" Mchj | J23: Ландиос Раствор для инфузий 100мл стеклянные флаконы | K23: 50 | L23: 64700 | M23: 3235000 | N23: 10 | O23: 323500
A24: 2026 | B24: 1 | C24: 46042 | D24: GB000000143 | E24: Мехриддин ака (Нав) | F24: Навоий_Мехриддин ака | G24: Козим ака | H24: GB | I24: "Navbahor Dori Ta`Minoti" Mchj | J24: Ландиос Раствор для инфузий 100мл стеклянные флаконы | K24: 20 | L24: 64700 | M24: 1294000 | N24: 10 | O24: 129400
A25: 2026 | B25: 1 | C25: 46042 | D25: GB000000144 | E25: Нигора (Тош) | F25: Ташкент_Дилнавоз опа | G25: Козим ака | H25: GB | I25: "Ashio Pharm" Mchj | J25: Эпсол раствор для инфузий 12 мг/мл 50 мл | K25: 10 | L25: 65000 | M25: 650000 | N25: 5 | O25: 32500
A26: 2026 | B26: 1 | C26: 46043 | D26: GB000000169 | E26: Ситора опа (Тош) | F26: Ташкент_Дилнавоз опа | G26: Козим ака | H26: GB | I26: "7777 Pharm" Mchj | J26: Ландиос Раствор для инфузий 100мл стеклянные флаконы | K26: 10 | L26: 64700 | M26: 647000 | N26: 5 | O26: 32350
A27: 2026 | B27: 1 | C27: 46043 | D27: GB000000169 | E27: Ситора опа (Тош) | F27: Ташкент_Дилнавоз опа | G27: Козим ака | H27: GB | I27: "7777 Pharm" Mchj | J27: Миранол раствор для инфузий 50 мл | K27: 10 | L27: 90000 | M27: 900000 | N27: 5 | O27: 45000
A28: 2026 | B28: 1 | C28: 46043 | D28: GB000000169 | E28: Ситора опа (Тош) | F28: Ташкент_Дилнавоз опа | G28: Козим ака | H28: GB | I28: "7777 Pharm" Mchj | J28: Эпсол раствор для инфузий 12 мг/мл 50 мл | K28: 10 | L28: 65000 | M28: 650000 | N28: 5 | O28: 32500
A29: 2026 | B29: 1 | C29: 46043 | D29: GB000000174 | E29: Дилором опа (Тош) | F29: Ташкент_Дилнавоз опа | G29: Козим ака | H29: GB | I29: "Bio Nur Med" Mchj | J29: Эпсол раствор для инфузий 12 мг/мл 50 мл | K29: 10 | L29: 65000 | M29: 650000 | N29: 5 | O29: 32500
A30: 2026 | B30: 1 | C30: 46043 | D30: GB000000175 | E30: Дилнавоз опа (Тош) | F30: Ташкент_Дилнавоз опа | G30: Козим ака | H30: GB | I30: "Madina Shifo Nur" Mchj | J30: Миранол раствор для инфузий 50 мл | K30: 20 | L30: 90000 | M30: 1800000 | N30: 5 | O30: 90000
A31: 2026 | B31: 1 | C31: 46043 | D31: GB000000175 | E31: Дилнавоз опа (Тош) | F31: Ташкент_Дилнавоз опа | G31: Козим ака | H31: GB | I31: "Madina Shifo Nur" Mchj | J31: Ландиос Раствор для инфузий 100мл стеклянные флаконы | K31: 20 | L31: 64700 | M31: 1294000 | N31: 5 | O31: 64700
A32: 2026 | B32: 1 | C32: 46043 | D32: GB000000175 | E32: Дилнавоз опа (Тош) | F32: Ташкент_Дилнавоз опа | G32: Козим ака | H32: GB | I32: "Madina Shifo Nur" Mchj | J32: Эпсол раствор для инфузий 12 мг/мл 50 мл | K32: 20 | L32: 65000 | M32: 1300000 | N32: 5 | O32: 65000
A33: 2026 | B33: 1 | C33: 46044 | D33: GB000000181 | E33: Дилнавоз опа (Тош) | F33: Ташкент_Дилнавоз опа | G33: Козим ака | H33: GB | I33: "Tosh-Po'lat Pharm" Mchj | J33: Эпсол раствор для инфузий 12 мг/мл 50 мл | K33: 20 | L33: 65000 | M33: 1300000 | N33: 5 | O33: 65000
... A49: 2026 | B49: 1 | C49: 46052 | D49: GB000000281 | E49: Мехриддин ака (Нав) | F49: Навоий_Мехриддин ака | G49: Козим ака | H49: GB | I49: "Fito-Farm-Lek" Mchj | J49: Ландиос Раствор для инфузий 100мл стеклянные флаконы | K49: 10 | L49: 64700 | M49: 647000 | N49: 8 | O49: 51760
A50: 2026 | B50: 2 | C50: 46055 | D50: GB000000297 | F50: Навоий_Мехриддин ака | G50: Козим ака | H50: GB | I50: "Zulfiya Med Farm 77" Xk | J50: Ландиос Раствор для инфузий 100мл стеклянные флаконы | K50: 20 | L50: 64700 | M50: 1294000 | N50: 10 | O50: 129400
A51: 2026 | B51: 2 | C51: 46055 | D51: GB000000297 | F51: Навоий_Мехриддин ака | G51: Козим ака | H51: GB | I51: "Zulfiya Med Farm 77" Xk | J51: Ландиос Раствор для инфузий 100мл стеклянные флаконы | K51: 20 | L51: 64700 | M51: 1294000 | N51: 10 | O51: 129400
A52: 2026 | B52: 2 | C52: 46056 | D52: GB000000300 | E52: Дилнавоз опа (Тош) | F52: Ташкент_Дилнавоз опа | G52: Козим ака | H52: GB | I52: "Tosh-Po'lat Pharm" Mchj | J52: Миранол раствор для инфузий 50 мл | K52: 20 | L52: 90000 | M52: 1800000 | N52: 5 | O52: 90000
A53: 2026 | B53: 2 | C53: 46056 | D53: GB000000300 | E53: Дилнавоз опа (Тош) | F53: Ташкент_Дилнавоз опа | G53: Козим ака | H53: GB | I53: "Tosh-Po'lat Pharm" Mchj | J53: Ландиос Раствор для инфузий 100мл стеклянные флаконы | K53: 30 | L53: 64700 | M53: 1941000 | N53: 5 | O53: 97050
A54: 2026 | B54: 2 | C54: 46056 | D54: GB000000300 | E54: Дилнавоз опа (Тош) | F54: Ташкент_Дилнавоз опа | G54: Козим ака | H54: GB | I54: "Tosh-Po'lat Pharm" Mchj | J54: Эпсол раствор для инфузий 12 мг/мл 50 мл | K54: 20 | L54: 65000 | M54: 1300000 | N54: 5 | O54: 65000
A55: 2026 | B55: 2 | C55: 46056 | D55: GB000000303 | E55: Мехриддин ака (Нав) | F55: Навоий_Мехриддин ака | G55: Козим ака | H55: GB | I55: "Navbahor Dori Ta`Minoti" Mchj | J55: Ландиос Раствор для инфузий 100мл стеклянные флаконы | K55: 20 | L55: 64700 | M55: 1294000 | N55: 10 | O55: 129400
A56: 2026 | B56: 2 | C56: 46057 | D56: GB000000323 | E56: Дилором опа (Тош) | F56: Ташкент_Дилнавоз опа | G56: Козим ака | H56: GB | I56: "Chiroy-Pharm" Mchj | J56: Эпсол раствор для инфузий 12 мг/мл 50 мл | K56: 20 | L56: 65000 | M56: 1300000 | N56: 5 | O56: 65000
A57: 2026 | B57: 2 | C57: 46057 | D57: GB000000324 | E57: Мехриддин ака (Нав) | F57: Навоий_Мехриддин ака | G57: Козим ака | H57: GB | I57: "Azam - Asror" Xk | J57: Ландиос Раствор для инфузий 100мл стеклянные флаконы | K57: 25 | L57: 64700 | M57: 1617500 | N57: 10 | O57: 161750
A58: 2026 | B58: 2 | C58: 46057 | D58: GB000000326 | E58: Дилором опа (Тош) | F58: Ташкент_Дилнавоз опа | G58: Козим ака | H58: GB | I58: "Farhod Buyuk Farm" Mchj | J58: Эпсол раствор для инфузий 12 мг/мл 50 мл | K58: 48 | L58: 65000 | M58: 3120000 | N58: 5 | O58: 156000
A59: 2026 | B59: 2 | C59: 46057 | D59: GB000000326 | E59: Дилором опа (Тош) | F59: Ташкент_Дилнавоз опа | G59: Козим ака | H59: GB | I59: "Farhod Buyuk Farm" Mchj | J59: Эпсол раствор для инфузий 12 мг/мл 50 мл | K59: 2 | L59: 65000 | M59: 130000 | N59: 5 | O59: 6500
A60: 2026 | B60: 2 | C60: 46058 | D60: GB000000341 | E60: Нигора (Тош) | F60: Ташкент_Дилнавоз опа | G60: Козим ака | H60: GB | I60: "Pharm 999" Mchj | J60: Эпсол раствор для инфузий 12 мг/мл 50 мл | K60: 50 | L60: 65000 | M60: 3250000 | N60: 5 | O60: 162500
A61: 2026 | B61: 2 | C61: 46062 | D61: GB000000374 | E61: Дилором опа (Тош) | F61: Ташкент_Дилнавоз опа | G61: Козим ака | H61: GB | I61: "Akbar Pharm Servis" Mchj | J61: Миранол раствор для инфузий 50 мл | K61: 10 | L61: 90000 | M61: 900000 | N61: 5 | O61: 45000
A62: 2026 | B62: 2 | C62: 46062 | D62: GB000000380 | E62: Ситора опа (Тош) | F62: Ташкент_Дилнавоз опа | G62: Козим ака | H62: GB | I62: "Prosperiti-Farm" Mchj | J62: Миранол раствор для инфузий 50 мл | K62: 20 | L62: 90000 | M62: 1800000 | N62: 5 | O62: 90000
A63: 2026 | B63: 2 | C63: 46062 | D63: GB000000385 | E63: Ситора опа (Тош) | F63: Ташкент_Дилнавоз опа | G63: Козим ака | H63: GB | I63: "7777 Pharm" Mchj | J63: Миранол раствор для инфузий 50 мл | K63: 20 | L63: 90000 | M63: 1800000 | N63: 5 | O63: 90000
... A98: 2026 | B98: 2 | C98: 46073 | D98: GB000000562 | E98: Дилнавоз опа (Тош) | F98: Ташкент_Дилнавоз опа | G98: Козим ака | H98: GB | I98: "Aero Pharm Pharmacy" Mchj | J98: Миранол раствор для инфузий 50 мл | K98: 15 | L98: 90000 | M98: 1350000 | N98: 5 | O98: 67500
A99: 2026 | B99: 2 | C99: 46076 | D99: GB000000013 | F99: Навоий_Мехриддин ака | G99: Козим ака | H99: GB | I99: "Zulfiya Med Farm 77" Xk | J99: Ландиос Раствор для инфузий 100мл стеклянные флаконы | K99: -20 | L99: 64700 | M99: -1294000 | N99: 10 | O99: 129400
A100: 2026 | B100: 2 | C100: 46076 | D100: GB000000013 | F100: Навоий_Мехриддин ака | G100: Козим ака | H100: GB | I100: "Zulfiya Med Farm 77" Xk | J100: Ландиос Раствор для инфузий 100мл стеклянные флаконы | K100: -20 | L100: 64700 | M100: -1294000 | N100: 10 | O100: 129400
A101: 2026 | B101: 2 | C101: 46076 | D101: GB000000567 | E101: Дилором опа (Тош) | F101: Ташкент_Дилнавоз опа | G101: Козим ака | H101: GB | I101: "Yasmina Omad Farm" Mchj | J101: Эпсол раствор для инфузий 12 мг/мл 50 мл | K101: 20 | L101: 65000 | M101: 1300000 | N101: 5 | O101: 65000
A102: 2026 | B102: 2 | C102: 46076 | D102: GB000000573 | E102: Дилором опа (Тош) | F102: Ташкент_Дилнавоз опа | G102: Козим ака | H102: GB | I102: "Akbar Pharm Servis" Mchj | J102: Миранол раствор для инфузий 50 мл | K102: 50 | L102: 90000 | M102: 4500000 | N102: 5 | O102: 225000
A103: 2026 | B103: 2 | C103: 46076 | D103: GB000000576 | E103: Мехриддин ака (Нав) | F103: Навоий_Мехриддин ака | G103: Козим ака | H103: GB | I103: "Everest Medical Center" Mchj | J103: Ландиос Раствор для инфузий 100мл стеклянные флаконы | K103: 13 | L103: 64700 | M103: 841100 | N103: 10 | O103: 84110
A104: 2026 | B104: 2 | C104: 46076 | D104: GB000000580 | E104: Дилнавоз опа (Тош) | F104: Ташкент_Дилнавоз опа | G104: Козим ака | H104: GB | I104: "Madina Shifo Nur" Mchj | J104: Эпсол раствор для инфузий 12 мг/мл 50 мл | K104: 10 | L104: 65000 | M104: 650000 | N104: 5 | O104: 32500
A105: 2026 | B105: 2 | C105: 46076 | D105: GB000000589 | E105: Мехриддин ака (Нав) | F105: Навоий_Мехриддин ака | G105: Козим ака | H105: GB | I105: "NUR ZIYO SHER" mas`uliyati cheklangan jamiyati | J105: Ландиос Раствор для инфузий 100мл стеклянные флаконы | K105: 20 | L105: 64700 | M105: 1294000 | N105: 10 | O105: 129400
A106: 2026 | B106: 2 | C106: 46077 | D106: GB000000594 | E106: Дилнавоз опа (Тош) | F106: Ташкент_Дилнавоз опа | G106: Козим ака | H106: GB | I106: "7777 Pharm" Mchj | J106: Ландиос Раствор для инфузий 100мл стеклянные флаконы | K106: 30 | L106: 64700 | M106: 1941000 | N106: 5 | O106: 97050
A107: 2026 | B107: 2 | C107: 46077 | D107: GB000000594 | E107: Дилнавоз опа (Тош) | F107: Ташкент_Дилнавоз опа | G107: Козим ака | H107: GB | I107: "7777 Pharm" Mchj | J107: Миранол раствор для инфузий 50 мл | K107: 30 | L107: 90000 | M107: 2700000 | N107: 5 | O107: 135000
A108: 2026 | B108: 2 | C108: 46077 | D108: GB000000594 | E108: Дилнавоз опа (Тош) | F108: Ташкент_Дилнавоз опа | G108: Козим ака | H108: GB | I108: "7777 Pharm" Mchj | J108: Эпсол раствор для инфузий 12 мг/мл 50 мл | K108: 30 | L108: 65000 | M108: 1950000 | N108: 5 | O108: 97500
A109: 2026 | B109: 2 | C109: 46078 | D109: GB000000609 | E109: Дилором опа (Тош) | F109: Ташкент_Дилнавоз опа | G109: Козим ака | H109: GB | I109: "Diyor-Farm" Mchj | J109: Миранол раствор для инфузий 50 мл | K109: 10 | L109: 90000 | M109: 900000 | N109: 5 | O109: 45000
A110: 2026 | B110: 2 | C110: 46078 | D110: GB000000614 | E110: Дилором опа (Тош) | F110: Ташкент_Дилнавоз опа | G110: Козим ака | H110: GB | I110: "Damin Gulchehra Farm" Mchj | J110: Миранол раствор для инфузий 50 мл | K110: 10 | L110: 90000 | M110: 900000 | N110: 5 | O110: 45000
A111: 2026 | B111: 2 | C111: 46078 | D111: GB000000616 | E111: Дилором опа (Тош) | F111: Ташкент_Дилнавоз опа | G111: Козим ака | H111: GB | I111: "Nata Vigor Pharm" Mchj | J111: Миранол раствор для инфузий 50 мл | K111: 17 | L111: 90000 | M111: 1530000 | N111: 5 | O111: 76500
A112: 2026 | B112: 2 | C112: 46078 | D112: GB000000616 | E112: Дилором опа (Тош) | F112: Ташкент_Дилнавоз опа | G112: Козим ака | H112: GB | I112: "Nata Vigor Pharm" Mchj | J112: Эпсол раствор для инфузий 12 мг/мл 50 мл | K112: 13 | L112: 65000 | M112: 845000 | N112: 5 | O112: 42250
... A256: 2026 | B256: 5 | C256: 46157 | D256: GB000001413 | E256: Махфуза опа (Тош) | F256: Ташкент_Дилнавоз опа | G256: Козим ака | H256: GB | I256: "Madina Shifo Nur" Mchj | J256: Миранол раствор для инфузий 50 мл | K256: 29 | L256: 90000 | M256: 2610000 | N256: 5 | O256: 130500

Sheet RMF
K1: =SUBTOTAL(9,K3:K1048576) -> 37531 | M1: =SUBTOTAL(9,M3:M1048576) -> 2661520912
A2: Год | B2: Месяц | C2: Дата | D2: Номер СФ | E2: Медпредставитель | F2: Команда | G2: РМ | H2: Поставщик | I2: Название организации | J2: Наименование | K2: Количество | L2: Цена | M2: Сумма | N2: % наценки | O2: Сумма наценки
A3: 2025 | B3: 10 | C3: 45933 | D3: RMF00004990 | E3: Хуршид ака (Сам) | F3: Самарканд_Хуршед ака | G3: Алишер | H3: RMF | I3: "Isayev Farm 777" Mchj | J3: Эльфор р-р. для инф 5м/мл | K3: 100 | L3: 40621 | M3: 4062100 | N3: 15 | O3: 609315
A4: 2025 | B4: 10 | C4: 45933 | D4: RMF00004995 | E4: Хуршид ака (Сам) | F4: Самарканд_Хуршед ака | G4: Алишер | H4: RMF | I4: "Azamat Gold Farm" Mchj | J4: Эльфор р-р. для инф 5м/мл | K4: 30 | L4: 40621 | M4: 1218630 | N4: 15 | O4: 182794.5
A5: 2025 | B5: 10 | C5: 45939 | D5: RMF00005090 | E5: Улугбек ака (Хор) | F5: Хоразм_Улугбек ака | G5: Алишер | H5: RMF | I5: "Intermed Pharmaceutical" Mchj | J5: Эпсол раствор для инфузий 12 мг/мл 50 мл | K5: 100 | L5: 52500 | M5: 5250000 | N5: 12 | O5: 630000
A6: 2025 | B6: 10 | C6: 45939 | D6: RMF00005090 | E6: Улугбек ака (Хор) | F6: Хоразм_Улугбек ака | G6: Алишер | H6: RMF | I6: "Intermed Pharmaceutical" Mchj | J6: Миранол раствор для инфузий 50 мл | K6: 100 | L6: 67600 | M6: 6760000 | N6: 15 | O6: 1014000
A7: 2025 | B7: 10 | C7: 45939 | D7: RMF00005100 | E7: Умар ака (Фр) | F7: Фаргона_Умар ака Сух | G7: Алишер | H7: RMF | I7: "Sezon Ntd" Xk | J7: Эпсол раствор для инфузий 12 мг/мл 50 мл | K7: 10 | L7: 52500 | M7: 525000 | N7: 15 | O7: 78750
A8: 2025 | B8: 10 | C8: 45939 | D8: RMF00005100 | E8: Умар ака (Фр) | F8: Фаргона_Умар ака Сух | G8: Алишер | H8: RMF | I8: "Sezon Ntd" Xk | J8: Миранол раствор для инфузий 50 мл | K8: 30 | L8: 67600 | M8: 2028000 | N8: 15 | O8: 304200
A9: 2025 | B9: 10 | C9: 45940 | D9: RMF00005113 | E9: Фотима опа (Сир) | F9: Сирдарё_Фотима опа | G9: Алишер | H9: RMF | I9: "Rustambek-J.b.b." Xk | J9: Эпсол раствор для инфузий 12 мг/мл 50 мл | K9: 30 | L9: 52500 | M9: 1575000 | N9: 15 | O9: 236250
A10: 2025 | B10: 10 | C10: 45945 | D10: RMF00005164 | E10: Абдушукур ака (Сир) | F10: Сирдарё_Фотима опа | G10: Алишер | H10: RMF | I10: "Baxtiyor Turg'unovich" Ktxf | J10: Софин раствор для инфузий 5% 100 мл | K10: 30 | L10: 120000 | M10: 3600000 | N10: 15 | O10: 540000
A11: 2025 | B11: 10 | C11: 45946 | D11: RMF00005180 | E11: Профи | F11: Профи | G11: Профи | H11: RMF | I11: "Profi Pharm Service" Mchj | J11: Софин раствор для инфузий 5% 100 мл | K11: 500 | L11: 120000 | M11: 60000000 | N11: 2 | O11: 1200000
A12: 2025 | B12: 10 | C12: 45950 | D12: RMF00005213 | E12: Хуршид ака (Сам) | F12: Самарканд_Хуршед ака | G12: Алишер | H12: RMF | I12: "Max Mir Farm777" Mchj | J12: Эльфор р-р. для инф 5м/мл | K12: 200 | L12: 40621 | M12: 8124200 | N12: 15 | O12: 1218630
A13: 2025 | B13: 10 | C13: 45950 | D13: RMF00005223 | E13: Мехрибон опа (Нк) | F13: Нукус_Мехрибон опа | G13: Алишер | H13: RMF | I13: "Mir Apteka" Mchj | J13: Миранол раствор для инфузий 50 мл | K13: 100 | L13: 90000 | M13: 9000000 | N13: 15 | O13: 1350000
A14: 2025 | B14: 10 | C14: 45951 | D14: RMF00005226 | E14: Фотима опа (Сир) | F14: Сирдарё_Фотима опа | G14: Алишер | H14: RMF | I14: "Ozodbek-Yan-Farm" Xk | J14: Софин раствор для инфузий 5% 100 мл | K14: 20 | L14: 120000 | M14: 2400000 | N14: 15 | O14: 360000
... A439: 2026 | B439: 5 | C439: 46148 | D439: RMF00001300 | E439: Профи | F439: Профи | G439: Профи | H439: RMF | I439: "Profi Pharm Service" Mchj | J439: Эпсол раствор для инфузий 12 мг/мл 50 мл | K439: 350 | L439: 65000 | M439: 22750000 | N439: 2 | O439: 455000

Sheet SFM
K1: =SUBTOTAL(9,K3:K1048576) -> 8573 | M1: =SUBTOTAL(9,M3:M1048576) -> 4.2949169e+08
A2: Год | B2: Месяц | C2: Дата | D2: Номер СФ | E2: Медпредставитель | F2: Команда | G2: РМ | H2: Поставщик | I2: Название организации | J2: Наименование | K2: Количество | L2: Цена | M2: Сумма | N2: % наценки | O2: Сумма наценки
A3: 2025 | B3: 4 | C3: 45770 | D3: SM000001337 | E3: PPS | F3: Тошкент_0 | G3: PPS | H3: SM | I3: "Profi Pharm Service" Mchj | J3: Эльфор р-р. для инф 5м/мл | K3: 2040 | L3: 36955.08 | M3: 75388363 | N3: 4 | O3: 3015534.5
A4: 2025 | B4: 5 | C4: 45803 | D4: SM000002015 | E4: Жонибек ака (Анд) | F4: Андижон_Жонибек ака | G4: Козим ака | H4: SM | I4: "Diyora Trade Pharm" Mchj | J4: Эльфор р-р. для инф 5м/мл | K4: 480 | L4: 36955.08 | M4: 17738438 | N4: 4 | O4: 709537.54
A5: 2025 | B5: 5 | C5: 45804 | D5: SM000002037 | E5: Феруза опа (Нам) | F5: Наманган_Розия опа | G5: Зикрулло ака | H5: SM | I5: "Zam-Zam Med Pharm" Mchj | J5: Эльфор р-р. для инф 5м/мл | K5: 300 | L5: 36955.08 | M5: 11086524 | N5: 8 | O5: 886921.92
A6: 2025 | B6: 5 | C6: 45806 | D6: SM000002089 | E6: Жонибек ака (Анд) | F6: <Объект не найден> (12090:95b918c04d74957511eeb48624412fc6) | H6: SM | I6: "Apteka Centr" Mchj | J6: Эльфор р-р. для инф 5м/мл | K6: 120 | L6: 36955.08 | M6: 4434609.6 | N6: 15 | O6: 665191.44
A7: 2025 | B7: 5 | C7: 45806 | D7: SM000002105 | E7: Феруза опа (Нам) | F7: Наманган_Розия опа | G7: Зикрулло ака | H7: SM | I7: "Mabda Healthcare Group" Mchj | J7: Эльфор р-р. для инф 5м/мл | K7: 20 | L7: 36955.08 | M7: 739101.6 | N7: 10 | O7: 73910.16
A8: 2025 | B8: 6 | C8: 45811 | D8: SM000002168 | E8: Феруза опа (Нам) | F8: Наманган_Розия опа | G8: Зикрулло ака | H8: SM | I8: "Aziz Shifo Farm" Ok | J8: Эльфор р-р. для инф 5м/мл | K8: 5 | L8: 36955.08 | M8: 184775.4 | N8: 13 | O8: 24020.8
A9: 2025 | B9: 6 | C9: 45833 | D9: SM000002503 | E9: Феруза опа (Нам) | F9: Наманган_Розия опа | G9: Зикрулло ака | H9: SM | I9: "Grand Pharm Andijon" Mchj | J9: Эльфор р-р. для инф 5м/мл | K9: 96 | L9: 36955.08 | M9: 3547687.7 | N9: 10 | O9: 354768.77
A10: 2025 | B10: 8 | C10: 45880 | D10: SM000003297 | E10: Жонибек ака (Анд) | F10: Андижон_Жонибек ака | G10: Козим ака | H10: SM | I10: "Diyora Trade Pharm" Mchj | J10: Эльфор р-р. для инф 5м/мл | K10: 480 | L10: 36955.08 | M10: 17738438 | N10: 4 | O10: 709537.54
A11: 2025 | B11: 8 | C11: 45888 | D11: SM000003430 | E11: Жонибек ака (Анд) | F11: <Объект не найден> (12090:95b918c04d74957511eeb48624412fc6) | H11: SM | I11: "Apteka Centr" Mchj | J11: Эльфор р-р. для инф 5м/мл | K11: 120 | L11: 36955.08 | M11: 4434609.6 | N11: 15 | O11: 665191.44
A12: 2025 | B12: 8 | C12: 45890 | D12: SM000003458 | E12: Жонибек ака (Анд) | F12: <Объект не найден> (12090:95b918c04d74957511eeb48624412fc6) | H12: SM | I12: "Mumiyo Dorixonalari Tarmog`I" Mchj | J12: Эльфор р-р. для инф 5м/мл | K12: 60 | L12: 36955.08 | M12: 2217304.8 | N12: 15 | O12: 332595.72
A13: 2025 | B13: 9 | C13: 45909 | D13: SM000003697 | E13: Жонибек ака (Анд) | F13: Андижон_Жонибек ака | G13: Козим ака | H13: SM | I13: "Diyora Trade Pharm" Mchj | J13: Эльфор р-р. для инф 5м/мл | K13: 355 | L13: 36955.08 | M13: 13119053 | N13: 4 | O13: 524762.14
A14: 2025 | B14: 9 | C14: 45915 | D14: SM000003798 | E14: Жонибек ака (Анд) | F14: Андижон_Жонибек ака | G14: Козим ака | H14: SM | I14: "Diyora Trade Pharm" Mchj | J14: Эльфор р-р. для инф 5м/мл | K14: 111 | L14: 40621 | M14: 4508931 | N14: 6 | O14: 270535.86
A15: 2025 | B15: 10 | C15: 45937 | D15: SM000004125 | E15: Жонибек ака (Анд) | F15: Андижон_Жонибек ака | G15: Козим ака | H15: SM | I15: "Apteka Centr" Mchj | J15: Эльфор р-р. для инф 5м/мл | K15: 200 | L15: 40621 | M15: 8124200 | N15: 15 | O15: 1218630
A16: 2025 | B16: 10 | C16: 45943 | D16: SM000004221 | E16: Жонибек ака (Анд) | F16: Андижон_Жонибек ака | G16: Козим ака | H16: SM | I16: "Diyora Trade Pharm" Mchj | J16: Эльфор р-р. для инф 5м/мл | K16: 360 | L16: 40621 | M16: 14623560 | N16: 6 | O16: 877413.6
A17: 2025 | B17: 10 | C17: 45952 | D17: SM000004372 | E17: Зулайхо опа (Нам) | F17: Наманган_Зулайхо опа | G17: Зикрулло ака | H17: SM | I17: "Bilolhon Med Farm Servis" Mchj | J17: Эльфор р-р. для инф 5м/мл | K17: 100 | L17: 40621 | M17: 4062100 | N17: 8 | O17: 324968
A18: 2025 | B18: 11 | C18: 45964 | D18: SM000004579 | E18: Зулайхо опа (Нам) | F18: Наманган_Зулайхо опа | G18: Зикрулло ака | H18: SM | I18: "Bilolhon Med Farm Servis" Mchj | J18: Эльфор р-р. для инф 5м/мл | K18: 200 | L18: 40621 | M18: 8124200 | N18: 8 | O18: 649936
A19: 2025 | B19: 11 | C19: 45964 | D19: SM000004579 | E19: Зулайхо опа (Нам) | F19: Наманган_Зулайхо опа | G19: Зикрулло ака | H19: SM | I19: "Bilolhon Med Farm Servis" Mchj | J19: Эльфор р-р. для инф 5м/мл | K19: 4 | L19: 36955.08 | M19: 147820.32 | N19: 8 | O19: 11825.63
A20: 2025 | B20: 11 | C20: 45964 | D20: SM000004586 | E20: Ахроржон ака (Фр) | F20: Фаргона_Ахроржон Ака | G20: Азизбек ака | H20: SM | I20: "Imbex Farm" Mchj | J20: Софин раствор для инфузий 5% 100 мл | K20: 8 | L20: 120000 | M20: 960000 | N20: 13 | O20: 124800
A21: 2025 | B21: 11 | C21: 45968 | D21: SM000004654 | E21: Ахроржон ака (Фр) | F21: Фаргона_Ахроржон Ака | G21: Азизбек ака | H21: SM | I21: "Pharm Gate Group" Mchj | J21: Софин раствор для инфузий 5% 100 мл | K21: 20 | L21: 120000 | M21: 2400000 | N21: 5 | O21: 120000
A22: 2025 | B22: 11 | C22: 45973 | D22: SM000004731 | E22: Ахроржон ака (Фр) | F22: Фаргона_Ахроржон Ака | G22: Азизбек ака | H22: SM | I22: "Rish Farm Medikal" Mchj | J22: Софин раствор для инфузий 5% 100 мл | K22: 2 | L22: 120000 | M22: 240000 | N22: 10 | O22: 24000
A23: 2025 | B23: 11 | C23: 45974 | D23: SM000004769 | E23: Ахроржон ака (Фр) | F23: Фаргона_Ахроржон Ака | G23: Азизбек ака | H23: SM | I23: "Anor Davo Farm" Mchj | J23: Софин раствор для инфузий 5% 100 мл | K23: 10 | L23: 120000 | M23: 1200000 | N23: 13 | O23: 156000
A24: 2025 | B24: 11 | C24: 45975 | D24: SM000004786 | E24: Зулайхо опа (Нам) | F24: Наманган_Зулайхо опа | G24: Зикрулло ака | H24: SM | I24: MCHJ Unf Innovation Farm | J24: Эльфор р-р. для инф 5м/мл | K24: 48 | L24: 40621 | M24: 1949808 | N24: 8 | O24: 155984.64
... A100: 2026 | B100: 5 | C100: 46157 | D100: SM000002468 | E100: Мусабек ака | F100: Кукон_Баходирхон ака | G100: Алишер | H100: SM | I100: "Grand Pharm Fergana" Mchj | J100: Ландиос Раствор для инфузий 100мл стеклянные флаконы | K100: 40 | L100: 64700 | M100: 2588000 | N100: 15 | O100: 388200

Sheet PPS2
K1: =SUBTOTAL(9,K3:K1048576) -> 81627 | M1: =SUBTOTAL(9,M3:M1048576) -> 820347000
A2: Год | B2: Месяц | C2: Дата | D2: Номер СФ | E2: Медпредставитель | F2: Команда | G2: РМ | H2: Поставщик | I2: Название организации | J2: Наименование | K2: Количество | L2: Цена | M2: Сумма
A3: 2025 | B3: 1 | C3: 45688 | D3: P2000000100 | E3: Хуршед ака | F3: Самарканд_Хуршид ака | G3: Зикрулло ака | H3: P2 | I3: Хуршид ака | J3: Эльфор р-р. для инф 5м/мл | K3: 7800 | L3: 16300 | M3: 127140000
A4: 2025 | B4: 1 | C4: 45688 | D4: P2000000101 | E4: Жонибек ака | F4: Андижон_Жонибек ака | G4: Зикрулло ака | H4: P2 | I4: Жонибек ака Андижон | J4: Эльфор р-р. для инф 5м/мл | K4: 5000
A5: 2025 | B5: 2 | C5: 45692 | D5: P2000000115 | E5: Жонибек ака | F5: Андижон_Жонибек ака | G5: Зикрулло ака | H5: P2 | I5: Жонибек ака Андижон | J5: Эльфор р-р. для инф 5м/мл | K5: 3000
A6: 2025 | B6: 2 | C6: 45698 | D6: P2000000139 | E6: Рустам ака | F6: Б2Б-Бухоро_Рустам ака | G6: Зикрулло ака | H6: P2 | I6: Б2Б-Бухоро_Рустам ака | J6: Эльфор р-р. для инф 5м/мл | K6: 5000
A7: 2025 | B7: 2 | C7: 45714 | D7: P2000000194 | E7: Розия опа | F7: Б2Б - Наманган_Розия опа | G7: Зикрулло ака | H7: P2 | I7: Розия опа | J7: Эльфор р-р. для инф 5м/мл | K7: 480
A8: 2025 | B8: 2 | C8: 45714 | D8: P2000000195 | E8: Рустам ака | F8: Таш.Обл_Рустам ака | G8: Зикрулло ака | H8: P2 | I8: Рустам ака Таш обл | J8: Эльфор р-р. для инф 5м/мл | K8: 1200
A9: 2025 | B9: 2 | C9: 45714 | D9: P2000000196 | E9: Фотима опа | F9: Сирдарьё_Фотима опа | H9: P2 | I9: Фотима опа | J9: Эльфор р-р. для инф 5м/мл | K9: 480
A10: 2025 | B10: 3 | C10: 45723 | D10: P2000000243 | E10: Сарвар ака | F10: Сурхондарьё_Сарвар ака | G10: Азизбек ака | H10: P2 | I10: Сарвар ака | J10: Эльфор р-р. для инф 5м/мл | K10: 500
A11: 2025 | B11: 4 | C11: 45768 | D11: P2000000380 | E11: Б2Б - Навоий_Гулшода опа | F11: Б2Б - Навоий_Гулшода опа | G11: Козим ака | H11: P2 | I11: Б2Б - Навоий_Гулшода опа | J11: Эльфор р-р. для инф 5м/мл | K11: 240
A12: 2025 | B12: 4 | C12: 45768 | D12: P2000000381 | E12: Б2Б - Наманган_Розия опа | F12: Б2Б - Наманган_Розия опа | G12: Зикрулло ака | H12: P2 | I12: Б2Б - Наманган_Розия опа | J12: Эльфор р-р. для инф 5м/мл | K12: 500
A13: 2025 | B13: 4 | C13: 45768 | D13: P2000000395 | E13: Сарвар ака | F13: Сурхондарьё_Сарвар ака | G13: Азизбек ака | H13: P2 | I13: Сарвар ака | J13: Эльфор р-р. для инф 5м/мл | K13: 600 | L13: 19000 | M13: 11400000
A14: 2025 | B14: 4 | C14: 45769 | D14: P2000000399 | E14: Б2Б - Хоразм_Саййора опа | F14: Б2Б - Хоразм_Саййора опа | G14: Зикрулло ака | H14: P2 | I14: Б2Б - Хоразм_Саййора опа | J14: Эльфор р-р. для инф 5м/мл | K14: 1200 | L14: 16300 | M14: 19560000
A15: 2025 | B15: 4 | C15: 45770 | D15: P2000000408 | E15: Жонибек ака | F15: Б2Б - Андижон Жонибек | G15: Жонибек ака | H15: P2 | I15: Жонибек ака Андижон | J15: Эльфор р-р. для инф 5м/мл | K15: 1200
A16: 2025 | B16: 4 | C16: 45770 | D16: P2000000409 | E16: Жонибек ака | F16: Б2Б - Андижон Жонибек | G16: Жонибек ака | H16: P2 | I16: Жонибек ака Андижон | J16: Эльфор р-р. для инф 5м/мл | K16: 1200
A17: 2025 | B17: 5 | C17: 45789 | D17: P2000000517 | E17: Нилюфар опа | F17: Кашкадарьё_Нилуфар опа | G17: Зикрулло ака | H17: P2 | I17: Нилюфар опа Карши | J17: Эльфор р-р. для инф 5м/мл | K17: 480
A18: 2025 | B18: 5 | C18: 45796 | D18: P2000000559 | E18: Рустам ака | F18: Б2Б - Тош обл Рустам ока | G18: Козим ака | H18: P2 | I18: Б2Б - Тош обл Рустам ока | J18: Эльфор р-р. для инф 5м/мл | K18: 480
A19: 2025 | B19: 5 | C19: 45799 | D19: P2000000587 | E19: Б2Б - Навоий_Гулшода опа | F19: Б2Б - Навоий_Гулшода опа | G19: Козим ака | H19: P2 | I19: Б2Б - Навоий_Гулшода опа | J19: Эльфор р-р. для инф 5м/мл | K19: 240
A20: 2025 | B20: 6 | C20: 45813 | D20: P2000000667 | E20: Рустам ака | F20: Б2Б - Тош обл Рустам ока | G20: Козим ака | H20: P2 | I20: Б2Б - Тош обл Рустам ока | J20: Эльфор р-р. для инф 5м/мл | K20: 480
A21: 2025 | B21: 6 | C21: 45818 | D21: P2000000683 | E21: Жонибек ака | F21: Андижон_Жонибек ака | G21: Зикрулло ака | H21: P2 | I21: Жонибек ака Андижон | J21: Эльфор р-р. для инф 5м/мл | K21: 1200
A22: 2025 | B22: 6 | C22: 45825 | D22: P2000000728 | E22: Рустам ака | F22: Б2Б - Тош обл Рустам ока | G22: Козим ака | H22: P2 | I22: Б2Б - Тош обл Рустам ока | J22: Эльфор р-р. для инф 5м/мл | K22: 480
A23: 2025 | B23: 6 | C23: 45827 | D23: P2000000748 | E23: Фотима опа | F23: Сирдарьё_Фотима опа | H23: P2 | I23: Фотима опа | J23: Эльфор р-р. для инф 5м/мл | K23: 100
A24: 2025 | B24: 6 | C24: 45828 | D24: P2000000762 | E24: Нилюфар опа | F24: Кашкадарьё_Нилуфар опа | G24: Зикрулло ака | H24: P2 | I24: Нилюфар опа Карши | J24: Эльфор р-р. для инф 5м/мл | K24: 1000
A25: 2025 | B25: 7 | C25: 45845 | D25: P2000000839 | E25: Рустам ака | F25: Таш.Обл_Рустам ака | G25: Зикрулло ака | H25: P2 | I25: Рустам ака Таш обл | J25: Эльфор р-р. для инф 5м/мл | K25: 480
A26: 2025 | B26: 7 | C26: 45845 | D26: P2000000840 | E26: Жонибек ака | F26: Андижон_Жонибек ака | G26: Зикрулло ака | H26: P2 | I26: Жонибек ака Андижон | J26: Эльфор р-р. для инф 5м/мл | K26: 1200
A27: 2025 | B27: 7 | C27: 45846 | D27: P2000000859 | E27: Б2Б - Хоразм_Саййора опа | F27: Б2Б - Хоразм_Саййора опа | G27: Зикрулло ака | H27: P2 | I27: Б2Б - Хоразм_Саййора опа | J27: Эльфор р-р. для инф 5м/мл | K27: 1500 | L27: 16300 | M27: 24450000
A28: 2025 | B28: 7 | C28: 45848 | D28: P2000000874 | E28: Сарвар ака | F28: Сурхондарьё_Сарвар ака | G28: Азизбек ака | H28: P2 | I28: Сарвар ака | J28: Эльфор р-р. для инф 5м/мл | K28: 500 | L28: 19000 | M28: 9500000
A29: 2025 | B29: 7 | C29: 45849 | D29: P2000000886 | E29: Фотима опа | F29: Сирдарьё_Фотима опа | H29: P2 | I29: Фотима опа | J29: Эльфор р-р. для инф 5м/мл | K29: 300
A30: 2025 | B30: 7 | C30: 45849 | D30: P2000000887 | E30: Фотима опа | F30: Сирдарьё_Фотима опа | H30: P2 | I30: Фотима опа | J30: Эльфор р-р. для инф 5м/мл | K30: 200
A31: 2025 | B31: 7 | C31: 45852 | D31: P2000000890 | E31: Нилюфар опа | F31: Кашкадарьё_Нилуфар опа | G31: Зикрулло ака | H31: P2 | I31: Нилюфар опа Карши | J31: Эльфор р-р. для инф 5м/мл | K31: 1000
A32: 2025 | B32: 7 | C32: 45853 | D32: P2000000904 | E32: Жонибек ака | F32: Андижон_Жонибек ака | G32: Зикрулло ака | H32: P2 | I32: Жонибек ака Андижон | J32: Эльфор р-р. для инф 5м/мл | K32: 2400
A33: 2025 | B33: 7 | C33: 45854 | D33: P2000000911 | E33: Рустам ака | F33: Бухоро_Рустам ака | G33: Зикрулло ака | H33: P2 | I33: Рустам ака | J33: Эльфор р-р. для инф 5м/мл | K33: 2000
A34: 2025 | B34: 7 | C34: 45855 | D34: P2000000926 | E34: Рустам ака | F34: Б2Б-Бухоро_Рустам ака | G34: Зикрулло ака | H34: P2 | I34: Б2Б-Бухоро_Рустам ака | J34: Эльфор р-р. для инф 5м/мл | K34: 480
A35: 2025 | B35: 8 | C35: 45875 | D35: P2000001027 | E35: Рустам ака | F35: Б2Б - Тош обл Рустам ока | G35: Козим ака | H35: P2 | I35: Б2Б - Тош обл Рустам ока | J35: Эльфор р-р. для инф 5м/мл | K35: 480
A36: 2025 | B36: 8 | C36: 45877 | D36: P2000001035 | E36: Нилюфар опа | F36: Кашкадарьё_Нилуфар опа | G36: Зикрулло ака | H36: P2 | I36: Нилюфар опа Карши | J36: Эльфор р-р. для инф 5м/мл | K36: 1000
A37: 2025 | B37: 8 | C37: 45884 | D37: P2000001063 | E37: Жонибек ака | F37: Б2Б - Андижон Жонибек | G37: Жонибек ака | H37: P2 | I37: Жонибек ака Андижон | J37: Эльфор р-р. для инф 5м/мл | K37: 720
A38: 2025 | B38: 8 | C38: 45888 | D38: P2000001071 | E38: Фотима опа | F38: Б2Б - Сирдаре Фотима опа | H38: P2 | I38: Фотима опа | J38: Эльфор р-р. для инф 5м/мл | K38: 100
A39: 2025 | B39: 8 | C39: 45889 | D39: P2000001077 | E39: Людмила опа | F39: Сурхондарьё_Людмила опа | G39: Азам ака | H39: P2 | I39: Людмила опа | J39: Эльфор р-р. для инф 5м/мл | K39: 1000 | L39: 18300 | M39: 18300000
A40: 2025 | B40: 8 | C40: 45889 | D40: P2000001085 | E40: Фотима опа | F40: Б2Б - Сирдаре Фотима опа | H40: P2 | I40: Фотима опа | J40: Эльфор р-р. для инф 5м/мл | K40: 100
A41: 2025 | B41: 8 | C41: 45891 | D41: P2000001107 | E41: Рустам ака | F41: Б2Б - Тош обл Рустам ока | G41: Козим ака | H41: P2 | I41: Б2Б - Тош обл Рустам ока | J41: Эльфор р-р. для инф 5м/мл | K41: 480
A42: 2025 | B42: 8 | C42: 45894 | D42: P2000001110 | E42: Жонибек ака | F42: Б2Б - Андижон Жонибек | G42: Жонибек ака | H42: P2 | I42: Жонибек ака Андижон | J42: Эльфор р-р. для инф 5м/мл | K42: 1200
A43: 2025 | B43: 8 | C43: 45894 | D43: P2000001112 | E43: Фотима опа | F43: Б2Б - Сирдаре Фотима опа | H43: P2 | I43: Фотима опа | J43: Эльфор р-р. для инф 5м/мл | K43: 120
A44: 2025 | B44: 9 | C44: 45904 | D44: P2000001145 | E44: Фотима опа | F44: Б2Б - Сирдаре Фотима опа | H44: P2 | I44: Фотима опа | J44: Эльфор р-р. для инф 5м/мл | K44: 120
A45: 2025 | B45: 9 | C45: 45908 | D45: P2000001151 | E45: Мохира опа | F45: Тошкент_Мохира опа | G45: Азам ака | H45: P2 | I45: Мохира опа | J45: Эльфор р-р. для инф 5м/мл | K45: 240 | L45: 18300 | M45: 4392000
A46: 2025 | B46: 9 | C46: 45909 | D46: P2000001160 | E46: Хуршида опа | F46: Самарканд_Хуршид ака | G46: Зикрулло ака | H46: P2 | I46: Хуршид ака | J46: Эльфор р-р. для инф 5м/мл | K46: 1440 | L46: 16300 | M46: 23472000
A47: 2025 | B47: 9 | C47: 45916 | D47: P2000001191 | E47: Жонибек ака | F47: Андижон_Жонибек ака | G47: Зикрулло ака | H47: P2 | I47: Жонибек ака Андижон | J47: Эльфор р-р. для инф 5м/мл | K47: 1200
A48: 2025 | B48: 9 | C48: 45916 | D48: P2000001196 | E48: Нилюфар опа | F48: Кашкадарьё_Нилуфар опа | G48: Зикрулло ака | H48: P2 | I48: Нилюфар опа Карши | J48: Эльфор р-р. для инф 5м/мл | K48: 1200
A49: 2025 | B49: 9 | C49: 45922 | D49: P2000001217 | E49: Рустам ака | F49: Таш.Обл_Рустам ака | G49: Зикрулло ака | H49: P2 | I49: Б2Б - Тош обл Рустам ока | J49: Эльфор р-р. для инф 5м/мл | K49: 480
A50: 2025 | B50: 9 | C50: 45929 | D50: P2000001253 | E50: Жонибек ака | F50: Андижон_Жонибек ака | G50: Зикрулло ака | H50: P2 | I50: Жонибек ака Андижон | J50: Эльфор р-р. для инф 5м/мл | K50: 480
A51: 2025 | B51: 9 | C51: 45929 | D51: P2000001254 | E51: Фотима опа | F51: Сирдарьё_Фотима опа | H51: P2 | I51: Фотима опа | J51: Эльфор р-р. для инф 5м/мл | K51: 300
A52: 2025 | B52: 10 | C52: 45933 | D52: P2000001269 | E52: Рустам ака | F52: Таш.Обл_Рустам ака | G52: Зикрулло ака | H52: P2 | I52: Б2Б - Тош обл Рустам ока | J52: Эльфор р-р. для инф 5м/мл | K52: 480
A53: 2025 | B53: 10 | C53: 45938 | D53: P2000001279 | E53: Шахло опа 2 | F53: Таш.Обл_Шахло опа | G53: Зикрулло ака | H53: P2 | I53: Шахло опа2 | J53: Софин раствор для инфузий 5% 100 мл | K53: 500 | L53: 55000 | M53: 27500000
A54: 2025 | B54: 10 | C54: 45940 | D54: P2000001292 | E54: Жонибек ака | F54: Андижон_Жонибек ака | G54: Зикрулло ака | H54: P2 | I54: Жонибек ака Андижон | J54: Эльфор р-р. для инф 5м/мл | K54: 480
A55: 2025 | B55: 10 | C55: 45947 | D55: P2000001331 | E55: Саййора опа | F55: Хоразм_Саййора опа | G55: Зикрулло ака | H55: P2 | I55: Саййора опа | J55: Эльфор р-р. для инф 5м/мл | K55: 400
A56: 2025 | B56: 10 | C56: 45953 | D56: P2000001352 | E56: Амангул опа | F56: Нукус_Амангуль опа | G56: Зикрулло ака | H56: P2 | I56: Амангул опа | J56: Софин раствор для инфузий 5% 100 мл | K56: 400 | L56: 50000 | M56: 20000000
A57: 2025 | B57: 10 | C57: 45953 | D57: P2000001354 | E57: Нилюфар опа | F57: Кашкадарьё_Нилуфар опа | G57: Зикрулло ака | H57: P2 | I57: Нилюфар опа Карши | J57: Эльфор р-р. для инф 5м/мл | K57: 1000
A58: 2025 | B58: 10 | C58: 45953 | D58: P2000001354 | E58: Нилюфар опа | F58: Кашкадарьё_Нилуфар опа | G58: Зикрулло ака | H58: P2 | I58: Нилюфар опа Карши | J58: Софин раствор для инфузий 5% 100 мл | K58: 200 | L58: 55000 | M58: 11000000
A59: 2025 | B59: 10 | C59: 45957 | D59: P2000001380 | E59: Жонибек ака | F59: Андижон_Жонибек ака | G59: Зикрулло ака | H59: P2 | I59: Жонибек ака Андижон | J59: Эльфор р-р. для инф 5м/мл | K59: 720
A60: 2025 | B60: 10 | C60: 45958 | D60: P2000001392 | E60: Хуршед ака | F60: Самарканд_Хуршид ака | G60: Зикрулло ака | H60: P2 | I60: Хуршид ака | J60: Эльфор р-р. для инф 5м/мл | K60: 480 | M60: 7824000
A61: 2025 | B61: 11 | C61: 45964 | D61: P2000001420 | E61: Рустам ака | F61: Таш.Обл_Рустам ака | G61: Зикрулло ака | H61: P2 | I61: Б2Б - Тош обл Рустам ока | J61: Эльфор р-р. для инф 5м/мл | K61: 480
A62: 2025 | B62: 11 | C62: 45964 | D62: P2000001422 | E62: Мафтуна опа | F62: Шахрисабз_Мафтуна опа | G62: Зикрулло ака | H62: P2 | I62: Мафтуна опа | J62: Софин раствор для инфузий 5% 100 мл | K62: 80 | L62: 55000 | M62: 4400000
A63: 2025 | B63: 11 | C63: 45967 | D63: P2000001433 | E63: Рустам ака | F63: Таш.Обл_Рустам ака | G63: Зикрулло ака | H63: P2 | I63: Рустам ака Таш обл | J63: Эльфор р-р. для инф 5м/мл | K63: 480
A64: 2025 | B64: 11 | C64: 45967 | D64: P2000001434 | E64: Жонибек ака | F64: Андижон_Жонибек ака | G64: Зикрулло ака | H64: P2 | I64: Жонибек ака Андижон | J64: Эльфор р-р. для инф 5м/мл | K64: 840
A65: 2025 | B65: 11 | C65: 45971 | D65: P2000001457 | E65: Людмила опа | F65: Сурхондарьё_Людмила опа | G65: Азам ака | H65: P2 | I65: Людмила опа | J65: Эльфор р-р. для инф 5м/мл | K65: 240 | L65: 18300 | M65: 4392000
A66: 2025 | B66: 11 | C66: 45973 | D66: P2000001473 | E66: Фотима опа | F66: Сирдарьё_Фотима опа | H66: P2 | I66: Фотима опа | J66: Эльфор р-р. для инф 5м/мл | K66: 100
A67: 2025 | B67: 11 | C67: 45973 | D67: P2000001480 | E67: Шахло опа 2 | F67: Таш.Обл_Шахло опа | G67: Зикрулло ака | H67: P2 | I67: Шахло опа2 | J67: Ландиос Раствор для инфузий 100 мл стеклянные флаконы | K67: 1000 | L67: 31000 | M67: 31000000
A68: 2025 | B68: 11 | C68: 45974 | D68: P2000001486 | E68: Жонибек ака | F68: Андижон_Жонибек ака | G68: Зикрулло ака | H68: P2 | I68: Жонибек ака Андижон | J68: Эльфор р-р. для инф 5м/мл | K68: 600
A69: 2025 | B69: 11 | C69: 45980 | D69: P2000001503 | E69: Жонибек ака | F69: Андижон_Жонибек ака | G69: Зикрулло ака | H69: P2 | I69: Жонибек ака Андижон | J69: Эльфор р-р. для инф 5м/мл | K69: 600
A70: 2025 | B70: 11 | C70: 45981 | D70: P2000001524 | E70: Амангул опа | F70: Нукус_Амангуль опа | G70: Зикрулло ака | H70: P2 | I70: Амангул опа | J70: Ландиос Раствор для инфузий 100 мл стеклянные флаконы | K70: 500 | L70: 31000 | M70: 15500000
A71: 2025 | B71: 11 | C71: 45981 | D71: P2000001524 | E71: Амангул опа | F71: Нукус_Амангуль опа | G71: Зикрулло ака | H71: P2 | I71: Амангул опа | J71: Софин раствор для инфузий 5% 100 мл | K71: 300 | L71: 50000 | M71: 15000000
A72: 2025 | B72: 11 | C72: 45981 | D72: P2000001524 | E72: Амангул опа | F72: Нукус_Амангуль опа | G72: Зикрулло ака | H72: P2 | I72: Амангул опа | J72: Эпсол раствор для инфузий 12 мг/мл 50 мл | K72: 300 | L72: 33000 | M72: 9900000
A73: 2025 | B73: 11 | C73: 45982 | D73: P2000001535 | E73: Ахрор ака | F73: Фаргона_Ахроржон Ака | G73: Азизбек ака | H73: P2 | I73: Ахроржон ака | J73: Софин раствор для инфузий 5% 100 мл | K73: 250 | L73: 50000 | M73: 12500000
A74: 2025 | B74: 11 | C74: 45985 | D74: P2000001541 | E74: Шахло опа 2 | F74: Таш.Обл_Шахло опа | G74: Зикрулло ака | H74: P2 | I74: Шахло опа2 | J74: Софин раствор для инфузий 5% 100 мл | K74: 400 | L74: 55000 | M74: 22000000
A75: 2025 | B75: 11 | C75: 45986 | D75: P2000001559 | E75: Жонибек ака | F75: Андижон_Жонибек ака | G75: Зикрулло ака | H75: P2 | I75: Жонибек ака Андижон | J75: Эльфор р-р. для инф 5м/мл | K75: 600
A76: 2025 | B76: 11 | C76: 45989 | D76: P2000001575 | E76: Жонибек ака | F76: Андижон_Жонибек ака | G76: Зикрулло ака | H76: P2 | I76: Жонибек ака Андижон | J76: Эльфор р-р. для инф 5м/мл | K76: 600
A77: 2025 | B77: 11 | C77: 45989 | D77: P2000001596 | E77: Амангул опа | F77: Нукус_Амангуль опа | G77: Зикрулло ака | H77: P2 | I77: Амангул опа | J77: Софин раствор для инфузий 5% 100 мл | K77: 50 | L77: 50000 | M77: 2500000
A78: 2025 | B78: 11 | C78: 45989 | D78: P2000001596 | E78: Амангул опа | F78: Нукус_Амангуль опа | G78: Зикрулло ака | H78: P2 | I78: Амангул опа | J78: Эпсол раствор для инфузий 12 мг/мл 50 мл | K78: 300 | L78: 33000 | M78: 9900000
A79: 2025 | B79: 12 | C79: 46001 | D79: P2000001641 | E79: Жонибек ака | F79: Андижон_Жонибек ака | G79: Зикрулло ака | H79: P2 | I79: Жонибек ака Андижон | J79: Эльфор р-р. для инф 5м/мл | K79: 600
A80: 2025 | B80: 12 | C80: 46001 | D80: P2000001644 | E80: Ахрор ака | F80: Фаргона_Ахроржон Ака | G80: Азизбек ака | H80: P2 | I80: Ахроржон ака | J80: Софин раствор для инфузий 5% 100 мл | K80: 300 | L80: 55000 | M80: 16500000
A81: 2025 | B81: 12 | C81: 46003 | D81: P2000001662 | E81: Нилюфар опа | F81: Кашкадарьё_Нилуфар опа | G81: Зикрулло ака | H81: P2 | I81: Нилюфар опа Карши | J81: Эльфор р-р. для инф 5м/мл | K81: 1000
A82: 2025 | B82: 12 | C82: 46007 | D82: P2000001681 | E82: Мафтуна опа | F82: Шахрисабз_Мафтуна опа | G82: Зикрулло ака | H82: P2 | I82: Мафтуна опа | J82: Софин раствор для инфузий 5% 100 мл | K82: 100 | L82: 55000 | M82: 5500000
A83: 2025 | B83: 12 | C83: 46007 | D83: P2000001682 | E83: Шахло опа 2 | F83: Таш.Обл_Шахло опа | G83: Зикрулло ака | H83: P2 | I83: Шахло опа2 | J83: Софин раствор для инфузий 5% 100 мл | K83: 400 | L83: 55000 | M83: 22000000
A84: 2025 | B84: 12 | C84: 46007 | D84: P2000001683 | E84: Жонибек ака | F84: Андижон_Жонибек ака | G84: Зикрулло ака | H84: P2 | I84: Жонибек ака Андижон | J84: Эльфор р-р. для инф 5м/мл | K84: 600 | L84: 16300 | M84: 9780000
A85: 2025 | B85: 12 | C85: 46008 | D85: P2000001687 | E85: Саййора опа | F85: Хоразм_Саййора опа | G85: Зикрулло ака | H85: P2 | I85: Саййора опа | J85: Эльфор р-р. для инф 5м/мл | K85: 1500
A86: 2025 | B86: 12 | C86: 46016 | D86: P2000001728 | E86: Амангул опа | F86: Нукус_Амангуль опа | G86: Зикрулло ака | H86: P2 | I86: Амангул опа | J86: Софин раствор для инфузий 5% 100 мл | K86: 385 | L86: 55000 | M86: 21175000
A87: 2025 | B87: 12 | C87: 46016 | D87: P2000001728 | E87: Амангул опа | F87: Нукус_Амангуль опа | G87: Зикрулло ака | H87: P2 | I87: Амангул опа | J87: Эпсол раствор для инфузий 12 мг/мл 50 мл | K87: 600 | L87: 33000 | M87: 19800000
A88: 2025 | B88: 12 | C88: 46017 | D88: P2000001733 | E88: Амангул опа | F88: Бухоро_Рустам ака | G88: Зикрулло ака | H88: P2 | I88: Рустам ака | J88: Эльфор р-р. для инф 5м/мл | K88: 80
A89: 2026 | B89: 1 | C89: 46041 | D89: P2000000013 | E89: Жонибек ака | F89: Андижон_Жонибек ака | G89: Зикрулло ака | H89: P2 | I89: Жонибек ака Андижон | J89: Эльфор р-р. для инф 5м/мл | K89: 600 | L89: 16300 | M89: 9780000
A90: 2026 | B90: 1 | C90: 46043 | D90: P2000000039 | E90: Ахрор ака | F90: Фаргона_Ахроржон Ака | G90: Азизбек ака | H90: P2 | I90: Ахроржон ака | J90: Софин раствор для инфузий 5% 100 мл | K90: 300 | L90: 55000 | M90: 16500000
A91: 2026 | B91: 1 | C91: 46044 | D91: P2000000043 | E91: Жонибек ака | F91: Андижон_Жонибек ака | G91: Зикрулло ака | H91: P2 | I91: Жонибек ака Андижон | J91: Эльфор р-р. для инф 5м/мл | K91: 600 | L91: 16300 | M91: 9780000
A92: 2026 | B92: 1 | C92: 46045 | D92: P2000000047 | E92: Людмила опа | F92: Сурхондарьё_Людмила опа | G92: Азам ака | H92: P2 | I92: Людмила опа | J92: Эльфор р-р. для инф 5м/мл | K92: 300 | L92: 18300 | M92: 5490000
A93: 2026 | B93: 1 | C93: 46045 | D93: P2000000050 | E93: Нилюфар опа | F93: Кашкадарьё_Нилуфар опа | G93: Зикрулло ака | H93: P2 | I93: Нилюфар опа Карши | J93: Эльфор р-р. для инф 5м/мл | K93: 687
A94: 2026 | B94: 1 | C94: 46048 | D94: P2000000061 | E94: Амангул опа | F94: Нукус_Амангуль опа | G94: Зикрулло ака | H94: P2 | I94: Амангул опа | J94: Софин раствор для инфузий 5% 100 мл | K94: 400 | L94: 55000 | M94: 22000000
A95: 2026 | B95: 1 | C95: 46048 | D95: P2000000065 | E95: Людмила опа | F95: Сурхондарьё_Людмила опа | G95: Азам ака | H95: P2 | I95: Людмила опа | J95: Эльфор р-р. для инф 5м/мл | K95: 400 | L95: 18300 | M95: 7320000
A96: 2026 | B96: 1 | C96: 46048 | D96: P2000000066 | E96: Нилюфар опа | F96: Кашкадарьё_Нилуфар опа | G96: Зикрулло ака | H96: P2 | I96: Нилюфар опа Карши | J96: Эльфор р-р. для инф 5м/мл | K96: 1000
A97: 2026 | B97: 1 | C97: 46051 | D97: P2000000087 | E97: Шахло опа 2 | F97: Таш.Обл_Шахло опа | G97: Зикрулло ака | H97: P2 | I97: Шахло опа2 | J97: Ландиос Раствор для инфузий 100 мл стеклянные флаконы | K97: 1200 | L97: 31000 | M97: 37200000
A98: 2026 | B98: 1 | C98: 46051 | D98: P2000000089 | E98: Людмила опа | F98: Сурхондарьё_Людмила опа | G98: Азам ака | H98: P2 | I98: Людмила опа | J98: Эльфор р-р. для инф 5м/мл | K98: 500 | L98: 18300 | M98: 9150000
A99: 2026 | B99: 2 | C99: 46058 | D99: P2000000130 | E99: Зикрулло ака | F99: Фарм фемили бизнес | G99: PPS | H99: P2 | I99: Фарм фемили бизнес | J99: Софин раствор для инфузий 5% 100 мл | K99: 5
A100: 2026 | B100: 2 | C100: 46064 | D100: P2000000158 | E100: Нилюфар опа | F100: Кашкадарьё_Нилуфар опа | G100: Зикрулло ака | H100: P2 | I100: Нилюфар опа Карши | J100: Софин раствор для инфузий 5% 100 мл | K100: 200 | L100: 55000 | M100: 11000000
...

Sheet IPS2
K1: =SUBTOTAL(9,K3:K1048576) -> 970 | M1: =SUBTOTAL(9,M3:M1048576) -> 12070000
A2: Год | B2: Месяц | C2: Дата | D2: Номер СФ | E2: Медпредставитель | F2: Команда | G2: РМ | H2: Поставщик | I2: Название организации | J2: Наименование | K2: Количество | L2: Цена | M2: Сумма
A3: 2025 | B3: 2 | C3: 45698 | D3: IP200000071 | E3: Фотима | F3: Сирдарьё_Фотима опа | G3: Козим ака | H3: IP2 | I3: Фотима опа | J3: Эльфор р-р. для инф 5м/мл | K3: 500
A4: 2025 | B4: 12 | C4: 45994 | D4: IP200000622 | E4: Элдор ака | F4: Ташкент_Дилнавоз опа | G4: Козим ака | H4: IP2 | I4: Элдор ака | J4: Ландиос Раствор для инфузий 100мл стеклянные флаконы | K4: 40
A5: 2025 | B5: 12 | C5: 45994 | D5: IP200000622 | E5: Элдор ака | F5: Ташкент_Дилнавоз опа | G5: Козим ака | H5: IP2 | I5: Элдор ака | J5: Миранол раствор для инфузий 50 мл | K5: 80 | L5: 20000 | M5: 1600000
A6: 2025 | B6: 12 | C6: 45994 | D6: IP200000622 | E6: Элдор ака | F6: Ташкент_Дилнавоз опа | G6: Козим ака | H6: IP2 | I6: Элдор ака | J6: Эпсол раствор для инфузий 12 мг/мл 50 мл | K6: 80 | L6: 16500 | M6: 1320000
A7: 2026 | B7: 1 | C7: 46028 | D7: IP200000003 | E7: Мехриддин ака | F7: Навоий_Мехриддин ака | G7: Козим ака | H7: IP2 | I7: Мехриддин ака | J7: Ландиос Раствор для инфузий 100мл стеклянные флаконы | K7: 20
A8: 2026 | B8: 1 | C8: 46045 | D8: IP200000025 | E8: Элдор ака | F8: Ташкент_Дилнавоз опа | G8: Козим ака | H8: IP2 | I8: Элдор ака | J8: Миранол раствор для инфузий 50 мл | K8: 30 | L8: 40000 | M8: 1200000
A9: 2026 | B9: 1 | C9: 46045 | D9: IP200000025 | E9: Элдор ака | F9: Ташкент_Дилнавоз опа | G9: Козим ака | H9: IP2 | I9: Элдор ака | J9: Эпсол раствор для инфузий 12 мг/мл 50 мл | K9: 20 | L9: 33000 | M9: 660000
A10: 2026 | B10: 1 | C10: 46052 | D10: IP200000041 | E10: Элдор ака | F10: Ташкент_Дилнавоз опа | G10: Козим ака | H10: IP2 | I10: Элдор ака | J10: Миранол раствор для инфузий 50 мл | K10: 20 | L10: 40000 | M10: 800000
A11: 2026 | B11: 2 | C11: 46071 | D11: IP200000093 | E11: Элдор ака | F11: Ташкент_Дилнавоз опа | G11: Козим ака | H11: IP2 | I11: Элдор ака | J11: Эпсол раствор для инфузий 12 мг/мл 50 мл | K11: 40 | L11: 33000 | M11: 1320000
A12: 2026 | B12: 3 | C12: 46094 | D12: IP200000123 | E12: Элдор ака | F12: Ташкент_Дилнавоз опа | G12: Козим ака | H12: IP2 | I12: Элдор ака | J12: Миранол раствор для инфузий 50 мл | K12: 40 | L12: 40000 | M12: 1600000
A13: 2026 | B13: 3 | C13: 46097 | D13: IP200000132 | E13: Элдор ака | F13: Ташкент_Дилнавоз опа | G13: Козим ака | H13: IP2 | I13: Элдор ака | J13: Миранол раствор для инфузий 50 мл | K13: 20 | L13: 40000 | M13: 800000
A14: 2026 | B14: 4 | C14: 46115 | D14: IP200000167 | E14: Элдор ака | F14: Ташкент_Дилнавоз опа | G14: Козим ака | H14: IP2 | I14: Элдор ака | J14: Миранол раствор для инфузий 50 мл | K14: 20 | L14: 40000 | M14: 800000
A15: 2026 | B15: 4 | C15: 46127 | D15: IP200000195 | E15: Элдор ака | F15: Ташкент_Дилнавоз опа | G15: Козим ака | H15: IP2 | I15: Элдор ака | J15: Миранол раствор для инфузий 50 мл | K15: 10 | L15: 40000 | M15: 400000
A16: 2026 | B16: 4 | C16: 46127 | D16: IP200000195 | E16: Элдор ака | F16: Ташкент_Дилнавоз опа | G16: Козим ака | H16: IP2 | I16: Элдор ака | J16: Эпсол раствор для инфузий 12 мг/мл 50 мл | K16: 10 | L16: 33000 | M16: 330000
A17: 2026 | B17: 5 | C17: 46154 | D17: IP200000233 | E17: Элдор ака | F17: Ташкент_Дилнавоз опа | G17: Козим ака | H17: IP2 | I17: Элдор ака | J17: Ландиос Раствор для инфузий 100мл стеклянные флаконы | K17: 40 | L17: 31000 | M17: 1240000

Sheet RMF2
K1: =SUBTOTAL(9,K3:K1048576) -> 43532 | M1: =SUBTOTAL(9,M3:M1048576) -> 1458185300
A2: Год | B2: Месяц | C2: Дата | D2: Номер СФ | E2: Медпредставитель | F2: Команда | G2: РМ | H2: Поставщик | I2: Название организации | J2: Наименование | K2: Количество | L2: Цена | M2: Сумма
A3: 2025 | B3: 10 | C3: 45940 | D3: R2000000374 | E3: Фотима опа | F3: Сирдарё_Фотима опа | G3: Алишер | H3: R2 | I3: Сирдарё_Фотима опа | J3: Софин раствор для инфузий 5% 100 мл | K3: 50 | L3: 50000 | M3: 2500000
A4: 2025 | B4: 10 | C4: 45940 | D4: R2000000374 | E4: Фотима опа | F4: Сирдарё_Фотима опа | G4: Алишер | H4: R2 | I4: Сирдарё_Фотима опа | J4: Эпсол раствор для инфузий 12 мг/мл 50 мл | K4: 50 | L4: 33000 | M4: 1650000
A5: 2025 | B5: 10 | C5: 45943 | D5: R2000000382 | E5: Улугбек ака | F5: Хоразм_Улугбек ака | G5: Алишер | H5: R2 | I5: Хоразм_Улугбек ака | J5: Миранол раствор для инфузий 50 мл | K5: 300 | L5: 38000 | M5: 11400000
A6: 2025 | B6: 10 | C6: 45943 | D6: R2000000382 | E6: Улугбек ака | F6: Хоразм_Улугбек ака | G6: Алишер | H6: R2 | I6: Хоразм_Улугбек ака | J6: Софин раствор для инфузий 5% 100 мл | K6: 300 | L6: 48000 | M6: 14400000
A7: 2025 | B7: 10 | C7: 45944 | D7: R2000000386 | E7: Андижон_Жонибек ака (S) | F7: Андижон_Жонибек ака (S) | G7: Алишер | H7: R2 | I7: Андижон_Жонибек ака (S) | J7: Софин раствор для инфузий 5% 100 мл | K7: 50 | L7: 50000 | M7: 2500000
A8: 2025 | B8: 10 | C8: 45944 | D8: R2000000387 | E8: Анвар ака | F8: Сурхондарьё_Анвар ака | G8: Алишер | H8: R2 | I8: Сурхондарьё_Анвар ака | J8: Софин раствор для инфузий 5% 100 мл | K8: 80 | L8: 50000 | M8: 4000000
A9: 2025 | B9: 10 | C9: 45944 | D9: R2000000387 | E9: Анвар ака | F9: Сурхондарьё_Анвар ака | G9: Алишер | H9: R2 | I9: Сурхондарьё_Анвар ака | J9: Эпсол раствор для инфузий 12 мг/мл 50 мл | K9: 100 | L9: 33000 | M9: 3300000
A10: 2025 | B10: 10 | C10: 45947 | D10: R2000000402 | E10: Умар | F10: Фаргона_Умар ака Сух | G10: Алишер | H10: R2 | I10: Фаргона_Умар ака Сух | J10: Эпсол раствор для инфузий 12 мг/мл 50 мл | K10: 40 | L10: 33000 | M10: 1320000
A11: 2025 | B11: 10 | C11: 45947 | D11: R2000000402 | E11: Умар | F11: Фаргона_Умар ака Сух | G11: Алишер | H11: R2 | I11: Фаргона_Умар ака Сух | J11: Миранол раствор для инфузий 50 мл | K11: 40 | L11: 40000 | M11: 1600000
A12: 2025 | B12: 10 | C12: 45951 | D12: R2000000420 | E12: Фотима опа | F12: Сирдарё_Фотима опа | G12: Алишер | H12: R2 | I12: Сирдарё_Фотима опа | J12: Миранол раствор для инфузий 50 мл | K12: 50 | L12: 40000 | M12: 2000000
A13: 2025 | B13: 10 | C13: 45951 | D13: R2000000422 | E13: Улугбек ака | F13: Хоразм_Улугбек ака | G13: Алишер | H13: R2 | I13: Хоразм_Улугбек ака | J13: Миранол раствор для инфузий 50 мл | K13: 200 | L13: 38000 | M13: 7600000
A14: 2025 | B14: 10 | C14: 45951 | D14: R2000000422 | E14: Улугбек ака | F14: Хоразм_Улугбек ака | G14: Алишер | H14: R2 | I14: Хоразм_Улугбек ака | J14: Софин раствор для инфузий 5% 100 мл | K14: 20 | L14: 48000 | M14: 960000
... A19: 2025 | B19: 10 | C19: 45957 | D19: R2000000438 | E19: Бахром ака | F19: Кукон_Бахромжон ака | G19: Алишер | H19: R2 | I19: Кукон_Бахромжон ака | J19: Софин раствор для инфузий 5% 100 мл | K19: 400 | L19: 50000 | M19: 20000000
A20: 2025 | B20: 10 | C20: 45960 | D20: R2000000450 | E20: ALIYEV KOZIMALI NOSIRALIYEVICH | F20: 11111 | H20: R2 | I20: Фарм фемили | J20: Эпсол раствор для инфузий 12 мг/мл 50 мл | K20: 20
A21: 2025 | B21: 11 | C21: 45964 | D21: R2000000458 | E21: Нукус_Мехрибон опа | F21: Нукус_Мехрибон опа | G21: Алишер | H21: R2 | I21: Нукус_Мехрибон опа | J21: Миранол раствор для инфузий 50 мл | K21: 100 | L21: 40000 | M21: 4000000
A22: 2025 | B22: 11 | C22: 45968 | D22: R2000000475 | E22: Хуршид ака | F22: Самарканд_Хуршед ака | G22: Алишер | H22: R2 | I22: Самарканд_Хуршед ака | J22: Миранол раствор для инфузий 50 мл | K22: 200 | L22: 40000 | M22: 8000000
A23: 2025 | B23: 11 | C23: 45971 | D23: R2000000482 | E23: Улугбек ака | F23: Хоразм_Улугбек ака | G23: Алишер | H23: R2 | I23: Хоразм_Улугбек ака | J23: Ландиос Раствор для инфузий 100мл стеклянные флаконы | K23: 600 | L23: 31000 | M23: 18600000
A24: 2025 | B24: 11 | C24: 45971 | D24: R2000000483 | E24: Гулшода опа | F24: Навоий_Гулшода опа | G24: Алишер | H24: R2 | I24: Навоий_Гулшода опа (S) | J24: Эпсол раствор для инфузий 12 мг/мл 50 мл | K24: 50 | L24: 33000 | M24: 1650000
A25: 2025 | B25: 11 | C25: 45972 | D25: R2000000485 | E25: Андижон_Жонибек ака (S) | F25: Андижон_Жонибек ака (S) | G25: Алишер | H25: R2 | I25: Андижон_Жонибек ака (S) | J25: Ландиос Раствор для инфузий 100мл стеклянные флаконы | K25: 200 | L25: 31000 | M25: 6200000
A26: 2025 | B26: 11 | C26: 45972 | D26: R2000000485 | E26: Андижон_Жонибек ака (S) | F26: Андижон_Жонибек ака (S) | G26: Алишер | H26: R2 | I26: Андижон_Жонибек ака (S) | J26: Эпсол раствор для инфузий 12 мг/мл 50 мл | K26: 100 | L26: 33000 | M26: 3300000
A27: 2025 | B27: 11 | C27: 45972 | D27: R2000000492 | E27: Хуршид ака | F27: Самарканд_Хуршед ака | G27: Алишер | H27: R2 | I27: Самарканд_Хуршед ака | J27: Софин раствор для инфузий 5% 100 мл | K27: 80 | L27: 50000 | M27: 4000000
A28: 2025 | B28: 11 | C28: 45972 | D28: R2000000494 | E28: Анвар ака | F28: Сурхондарьё_Анвар ака | G28: Алишер | H28: R2 | I28: Сурхондарьё_Анвар ака | J28: Миранол раствор для инфузий 50 мл | K28: 50 | L28: 40000 | M28: 2000000
A29: 2025 | B29: 11 | C29: 45972 | D29: R2000000494 | E29: Анвар ака | F29: Сурхондарьё_Анвар ака | G29: Алишер | H29: R2 | I29: Сурхондарьё_Анвар ака | J29: Эпсол раствор для инфузий 12 мг/мл 50 мл | K29: 100 | L29: 35000 | M29: 3500000
A30: 2025 | B30: 11 | C30: 45973 | D30: R2000000497 | E30: Рустам ака | F30: Таш.Обл_Рустам ака (S) | G30: Алишер | H30: R2 | I30: Таш.Обл_Рустам ака (S) | J30: Миранол раствор для инфузий 50 мл | K30: 400 | L30: 40000 | M30: 16000000
A31: 2025 | B31: 11 | C31: 45973 | D31: R2000000497 | E31: Рустам ака | F31: Таш.Обл_Рустам ака (S) | G31: Алишер | H31: R2 | I31: Таш.Обл_Рустам ака (S) | J31: Эпсол раствор для инфузий 12 мг/мл 50 мл | K31: 400 | L31: 33000 | M31: 13200000
A32: 2025 | B32: 11 | C32: 45974 | D32: R2000000500 | E32: Зафаржон ака | F32: Фаргона_Зафаржон ака | G32: Алишер | H32: R2 | I32: Фаргона_Зафаржон ака | J32: Ландиос Раствор для инфузий 100мл стеклянные флаконы | K32: 500 | L32: 31000 | M32: 15500000
... A73: 2025 | B73: 12 | C73: 46008 | D73: R2000000642 | E73: Хуршид ака | F73: Самарканд_Хуршед ака | G73: Алишер | H73: R2 | I73: Самарканд_Хуршед ака | J73: Эльфор р-р. для инф 5м/мл | K73: 90 | L73: 16300 | M73: 1467000
A74: 2025 | B74: 12 | C74: 46013 | D74: R2000000648 | E74: ALIYEV KOZIMALI NOSIRALIYEVICH | F74: списание | H74: R2 | I74: Списать | J74: Миранол раствор для инфузий 50 мл | K74: 50
A75: 2025 | B75: 12 | C75: 46013 | D75: R2000000649 | E75: Гулшода опа | F75: Навоий_Гулшода опа | G75: Алишер | H75: R2 | I75: Навоий_Гулшода опа (S) | J75: Софин раствор для инфузий 5% 100 мл | K75: 100 | L75: 50000 | M75: 5000000
A76: 2025 | B76: 12 | C76: 46014 | D76: R2000000651 | E76: Андижон_Жонибек ака (S) | F76: Андижон_Жонибек ака (S) | G76: Алишер | H76: R2 | I76: Андижон_Жонибек ака (S) | J76: Ландиос Раствор для инфузий 100мл стеклянные флаконы | K76: 40 | L76: 31000 | M76: 1240000
A77: 2025 | B77: 12 | C77: 46015 | D77: R2000000657 | E77: Хуршид ака | F77: Самарканд_Хуршед ака | G77: Алишер | H77: R2 | I77: Самарканд_Хуршед ака | J77: Эпсол раствор для инфузий 12 мг/мл 50 мл | K77: 50 | L77: 33000 | M77: 1650000
A78: 2026 | B78: 1 | C78: 46041 | D78: R2000000008 | E78: Анвар ака | F78: Сурхондарьё_Анвар ака | G78: Алишер | H78: R2 | I78: Сурхондарьё_Анвар ака | J78: Миранол раствор для инфузий 50 мл | K78: 50 | L78: 40000 | M78: 2000000
A79: 2026 | B79: 1 | C79: 46041 | D79: R2000000008 | E79: Анвар ака | F79: Сурхондарьё_Анвар ака | G79: Алишер | H79: R2 | I79: Сурхондарьё_Анвар ака | J79: Софин раствор для инфузий 5% 100 мл | K79: 80 | L79: 50000 | M79: 4000000
A80: 2026 | B80: 1 | C80: 46041 | D80: R2000000008 | E80: Анвар ака | F80: Сурхондарьё_Анвар ака | G80: Алишер | H80: R2 | I80: Сурхондарьё_Анвар ака | J80: Эпсол раствор для инфузий 12 мг/мл 50 мл | K80: 300 | L80: 33000 | M80: 9900000
A81: 2026 | B81: 1 | C81: 46041 | D81: R2000000009 | E81: Умар | F81: Фаргона_Умар ака Сух | G81: Алишер | H81: R2 | I81: Фаргона_Умар ака Сух | J81: Миранол раствор для инфузий 50 мл | K81: 50 | L81: 40000 | M81: 2000000
A82: 2026 | B82: 1 | C82: 46041 | D82: R2000000010 | E82: Хуршид ака | F82: Самарканд_Хуршед ака | G82: Алишер | H82: R2 | I82: Самарканд_Хуршед ака | J82: Софин раствор для инфузий 5% 100 мл | K82: 100 | L82: 50000 | M82: 5000000
A83: 2026 | B83: 1 | C83: 46041 | D83: R2000000010 | E83: Хуршид ака | F83: Самарканд_Хуршед ака | G83: Алишер | H83: R2 | I83: Самарканд_Хуршед ака | J83: Эльфор р-р. для инф 5м/мл | K83: 110 | L83: 16300 | M83: 1793000
A84: 2026 | B84: 1 | C84: 46041 | D84: R2000000013 | E84: Фотима опа | F84: Сирдарё_Фотима опа | G84: Алишер | H84: R2 | I84: Сирдарё_Фотима опа | J84: Эльфор р-р. для инф 5м/мл | K84: 50 | L84: 16300 | M84: 815000
A85: 2026 | B85: 1 | C85: 46041 | D85: R2000000013 | E85: Фотима опа | F85: Сирдарё_Фотима опа | G85: Алишер | H85: R2 | I85: Сирдарё_Фотима опа | J85: Эльфор р-р. для инф 5м/мл | K85: 250 | L85: 16300 | M85: 4075000
A86: 2026 | B86: 1 | C86: 46041 | D86: R2000000014 | E86: Андижон_Жонибек ака (S) | F86: Андижон_Жонибек ака (S) | G86: Алишер | H86: R2 | I86: Андижон_Жонибек ака (S) | J86: Ландиос Раствор для инфузий 100мл стеклянные флаконы | K86: 50 | L86: 31000 | M86: 1550000
... A118: 2026 | B118: 2 | C118: 46056 | D118: R2000000081 | E118: Анвар ака | F118: Сурхондарьё_Анвар ака | G118: Алишер | H118: R2 | I118: Сурхондарьё_Анвар ака | J118: Миранол раствор для инфузий 50 мл | K118: 50 | L118: 40000 | M118: 2000000
A119: 2026 | B119: 2 | C119: 46056 | D119: R2000000083 | E119: ALIYEV KOZIMALI NOSIRALIYEVICH | F119: списание | H119: R2 | I119: Списать | J119: Эльфор р-р. для инф 5м/мл | K119: 170
A120: 2026 | B120: 2 | C120: 46056 | D120: R2000000084 | E120: Хуршид ака | F120: Самарканд_Хуршед ака | G120: Алишер | H120: R2 | I120: Самарканд_Хуршед ака | J120: Эльфор р-р. для инф 5м/мл | K120: 95 | L120: 16300 | M120: 1548500
A121: 2026 | B121: 2 | C121: 46056 | D121: R2000000086 | E121: Хуршид ака | F121: Самарканд_Хуршед ака | G121: Алишер | H121: R2 | I121: Самарканд_Хуршед ака | J121: Миранол раствор для инфузий 50 мл | K121: 50 | L121: 40000 | M121: 2000000
A122: 2026 | B122: 2 | C122: 46058 | D122: R2000000090 | E122: Анвар ака | F122: Сурхондарьё_Анвар ака | G122: Алишер | H122: R2 | I122: Сурхондарьё_Анвар ака | J122: Эпсол раствор для инфузий 12 мг/мл 50 мл | K122: 800 | L122: 33000 | M122: 26400000
A123: 2026 | B123: 2 | C123: 46058 | D123: R2000000092 | E123: Бахром ака | F123: Кукон_Бахромжон ака | G123: Алишер | H123: R2 | I123: Кукон_Бахромжон ака | J123: Миранол раствор для инфузий 50 мл | K123: 200 | L123: 40000 | M123: 8000000
A124: 2026 | B124: 2 | C124: 46058 | D124: R2000000092 | E124: Бахром ака | F124: Кукон_Бахромжон ака | G124: Алишер | H124: R2 | I124: Кукон_Бахромжон ака | J124: Софин раствор для инфузий 5% 100 мл | K124: 200 | L124: 50000 | M124: 10000000
A125: 2026 | B125: 2 | C125: 46059 | D125: R2000000098 | E125: Андижон_Жонибек ака (S) | F125: Андижон_Жонибек ака (S) | G125: Алишер | H125: R2 | I125: Андижон_Жонибек ака (S) | J125: Эпсол раствор для инфузий 12 мг/мл 50 мл | K125: 40 | L125: 33000 | M125: 1320000
A126: 2026 | B126: 2 | C126: 46059 | D126: R2000000102 | E126: Хуршид ака | F126: Самарканд_Хуршед ака | G126: Алишер | H126: R2 | I126: Самарканд_Хуршед ака | J126: Эльфор р-р. для инф 5м/мл | K126: 240 | L126: 16300 | M126: 3912000
A127: 2026 | B127: 2 | C127: 46059 | D127: R2000000103 | E127: Рустам ака | F127: Таш.Обл_Рустам ака (S) | G127: Алишер | H127: R2 | I127: Таш.Обл_Рустам ака (S) | J127: Эльфор р-р. для инф 5м/мл | K127: 480 | L127: 16300 | M127: 7824000
A128: 2026 | B128: 2 | C128: 46059 | D128: R2000000104 | E128: Фотима опа | F128: Сирдарё_Фотима опа | G128: Алишер | H128: R2 | I128: Сирдарё_Фотима опа | J128: Эльфор р-р. для инф 5м/мл | K128: 50 | L128: 16300 | M128: 815000
A129: 2026 | B129: 2 | C129: 46059 | D129: R2000000105 | E129: Хуршид ака | F129: Самарканд_Хуршед ака | G129: Алишер | H129: R2 | I129: Самарканд_Хуршед ака | J129: Миранол раствор для инфузий 50 мл | K129: 50 | L129: 40000 | M129: 2000000
A130: 2026 | B130: 2 | C130: 46063 | D130: R2000000111 | E130: Фотима опа | F130: Сирдарё_Фотима опа | G130: Алишер | H130: R2 | I130: Сирдарё_Фотима опа | J130: Эльфор р-р. для инф 5м/мл | K130: 40 | L130: 16300 | M130: 652000
A131: 2026 | B131: 2 | C131: 46063 | D131: R2000000112 | E131: Хуршид ака | F131: Самарканд_Хуршед ака | G131: Алишер | H131: R2 | I131: Самарканд_Хуршед ака | J131: Миранол раствор для инфузий 50 мл | K131: 100 | L131: 40000 | M131: 4000000
... A169: 2026 | B169: 3 | C169: 46091 | D169: R2000000211 | E169: Анвар ака | F169: Сурхондарьё_Анвар ака | G169: Алишер | H169: R2 | I169: Сурхондарьё_Анвар ака | J169: Софин раствор для инфузий 5% 100 мл | K169: 100 | L169: 50000 | M169: 5000000
A170: 2026 | B170: 3 | C170: 46092 | D170: R2000000213 | E170: ALIYEV KOZIMALI NOSIRALIYEVICH | F170: списание | H170: R2 | I170: Списать | J170: Миранол раствор для инфузий 50 мл | K170: 819
A171: 2026 | B171: 3 | C171: 46092 | D171: R2000000214 | E171: Дилсуз опа | F171: Карши_Дилсўз опа | G171: Алишер | H171: R2 | I171: Карши_Дилсўз опа | J171: Миранол раствор для инфузий 50 мл | K171: 100 | L171: 40000 | M171: 4000000
A172: 2026 | B172: 3 | C172: 46092 | D172: R2000000218 | E172: Бахром ака | F172: Кукон_Бахромжон ака | G172: Алишер | H172: R2 | I172: Кукон_Бахромжон ака | J172: Миранол раствор для инфузий 50 мл | K172: 35 | L172: 40000 | M172: 1400000
A173: 2026 | B173: 3 | C173: 46092 | D173: R2000000218 | E173: Бахром ака | F173: Кукон_Бахромжон ака | G173: Алишер | H173: R2 | I173: Кукон_Бахромжон ака | J173: Миранол раствор для инфузий 50 мл | K173: 114 | L173: 40000 | M173: 4560000
A174: 2026 | B174: 3 | C174: 46092 | D174: R2000000218 | E174: Бахром ака | F174: Кукон_Бахромжон ака | G174: Алишер | H174: R2 | I174: Кукон_Бахромжон ака | J174: Миранол раствор для инфузий 50 мл | K174: 51 | L174: 40000 | M174: 2040000
A175: 2026 | B175: 3 | C175: 46092 | D175: R2000000218 | E175: Бахром ака | F175: Кукон_Бахромжон ака | G175: Алишер | H175: R2 | I175: Кукон_Бахромжон ака | J175: Софин раствор для инфузий 5% 100 мл | K175: 200 | L175: 50000 | M175: 10000000
A176: 2026 | B176: 3 | C176: 46093 | D176: R2000000220 | E176: Андижон_Жонибек ака (S) | F176: Андижон_Жонибек ака (S) | G176: Алишер | H176: R2 | I176: Андижон_Жонибек ака (S) | J176: Ландиос Раствор для инфузий 100мл стеклянные флаконы | K176: 120 | L176: 31000 | M176: 3720000
A177: 2026 | B177: 3 | C177: 46093 | D177: R2000000223 | E177: Гулшода опа | F177: Навоий_Гулшода опа | G177: Алишер | H177: R2 | I177: Навоий_Гулшода опа (S) | J177: Эпсол раствор для инфузий 12 мг/мл 50 мл | K177: 100 | L177: 33000 | M177: 3300000
A178: 2026 | B178: 3 | C178: 46097 | D178: R2000000226 | E178: Фотима опа | F178: Сирдарё_Фотима опа | G178: Алишер | H178: R2 | I178: Сирдарё_Фотима опа | J178: Софин раствор для инфузий 5% 100 мл | K178: 40 | L178: 50000 | M178: 2000000
A179: 2026 | B179: 3 | C179: 46098 | D179: R2000000229 | E179: Андижон_Жонибек ака (S) | F179: Андижон_Жонибек ака (S) | G179: Алишер | H179: R2 | I179: Андижон_Жонибек ака (S) | J179: Эпсол раствор для инфузий 12 мг/мл 50 мл | K179: 100 | L179: 33000 | M179: 3300000
A180: 2026 | B180: 3 | C180: 46098 | D180: R2000000230 | E180: Хуршид ака | F180: Самарканд_Хуршед ака | G180: Алишер | H180: R2 | I180: Самарканд_Хуршед ака | J180: Миранол раствор для инфузий 50 мл | K180: 50 | L180: 40000 | M180: 2000000
A181: 2026 | B181: 3 | C181: 46098 | D181: R2000000230 | E181: Хуршид ака | F181: Самарканд_Хуршед ака | G181: Алишер | H181: R2 | I181: Самарканд_Хуршед ака | J181: Эпсол раствор для инфузий 12 мг/мл 50 мл | K181: 50 | L181: 33000 | M181: 1650000
A182: 2026 | B182: 3 | C182: 46098 | D182: R2000000231 | E182: Нафосат опа | F182: Бухоро_Нафосат опа | G182: Алишер | H182: R2 | I182: Бухоро_Нафосат опа | J182: Миранол раствор для инфузий 50 мл | K182: 496 | L182: 40000 | M182: 19840000
... A266: 2026 | B266: 5 | C266: 46157 | D266: R2000000427 | E266: Фотима опа | F266: Сирдарё_Фотима опа | G266: Алишер | H266: R2 | I266: Сирдарё_Фотима опа | J266: Эпсол раствор для инфузий 12 мг/мл 50 мл | K266: 50 | L266: 33000 | M266: 1650000

Sheet Лист8
A3: Названия строк | B3: Сумма по полю сумма2
A4: Ландиос Раствор для инфузий 100мл стеклянные флаконы | B4: 151273764
A5: Миранол раствор для инфузий 50 мл | B5: 387865700
A6: Софин раствор для инфузий 5% 100 мл | B6: 284491760
A7: Эльфор р-р. для инф 5м/мл | B7: 6.0290864e+08
A8: Эпсол раствор для инфузий 12 мг/мл 50 мл | B8: 258213150
A9: Общий итог | B9: 1.684753e+09

Sheet Приход колва
A1: Приход
A2: 1 Epsol | B2: 17500
A3: 2 Epsol | B3: 16500
A4: Итого | B4: 34000
D5: Возврат
A6: 1 Miranol | B6: 27500 | D6: 0010825 | E6: 14319
A7: 2 Miranol | B7: 16700 | D7: 0010825 | E7: 1205
A8: Итого | B8: 44200 | D8: Итого | E8: 15524
A10: Приход
A11: 1 Sofin | B11: 19684
A12: 2 Sofin | B12: 14695
A13: Итого | B13: 34379
A16: Продажа
A17: 1 Landios | B17: 13400
A18: 2 Landios | B18: 18520
A19: Итого | B19: 31920
D23: =SUM(D25:D29) -> 3098101720
A24: Наименование | B24: Приход итого на Профи склад | C24: Цена завод | D24: Сумма итого
A25: Ландиос Раствор для инфузий 100мл стеклянные флаконы | B25: 31920 | C25: 18000 | D25: =+B25*C25 -> 574560000
A26: Эпсол раствор для инфузий 12 мг/мл 50 мл | B26: 34000 | C26: 20000 | D26: =+B26*C26 -> 680000000
A27: Софин раствор для инфузий 5% 100 мл | B27: 34379 | C27: 25000 | D27: =+B27*C27 -> 859475000
A28: Эльфор р-р. для инф 5м/мл | B28: 103320 | C28: =3696 -> 3696 | D28: =+B28*C28 -> 381870720
A29: Миранол раствор для инфузий 50 мл | B29: 28676 | C29: 21000 | D29: =+B29*C29 -> 602196000

Sheet Продажа 2
L1: =SUBTOTAL(9,L3:L389) -> 3112806200 | N1: =SUBTOTAL(9,N3:N389) -> 2721843000 | O1: =SUBTOTAL(9,O3:O389) -> 390963200
A2: Год | B2: Месяц | C2: Дата | D2: Номер СФ | E2: Медпредставитель | F2: Команда | G2: Поставщик | H2: Название организации | I2: Наименование | J2: Количество | K2: Цена | L2: Сумма | M2: Оплата | N2: Оплата | O2: Остаток долг
A3: 2025 | B3: 1 | C3: 45688 | D3: P2000000100 | E3: Хуршед ака | F3: Самарканд_Хуршид ака | G3: P2 | H3: Хуршид ака | I3: Эльфор р-р. для инф 5м/мл | J3: 7800 | K3: 16300 | L3: 127140000 | M3: 100 | N3: =+L3*M3% -> 127140000 | O3: =L3-N3 -> 0
A4: 2025 | B4: 1 | C4: 45688 | D4: P2000000101 | E4: Жонибек ака | F4: Андижон_Жонибек ака | G4: P2 | H4: Жонибек ака Андижон | I4: Эльфор р-р. для инф 5м/мл | J4: 5000 | K4: 16300 | L4: 81500000 | M4: 100 | N4: =+L4*M4% -> 81500000 | O4: =L4-N4 -> 0
A5: 2025 | B5: 2 | C5: 45692 | D5: P2000000115 | E5: Жонибек ака | F5: Андижон_Жонибек ака | G5: P2 | H5: Жонибек ака Андижон | I5: Эльфор р-р. для инф 5м/мл | J5: 3000 | K5: 16300 | L5: 48900000 | M5: 100 | N5: =+L5*M5% -> 48900000 | O5: =L5-N5 -> 0
A6: 2025 | B6: 2 | C6: 45698 | D6: P2000000139 | E6: Рустам ака | F6: Б2Б-Бухоро_Рустам ака | G6: P2 | H6: Б2Б-Бухоро_Рустам ака | I6: Эльфор р-р. для инф 5м/мл | J6: 5000 | K6: 18300 | L6: 91500000 | M6: 100 | N6: =+L6*M6% -> 91500000 | O6: =L6-N6 -> 0
A7: 2025 | B7: 2 | C7: 45714 | D7: P2000000194 | E7: Розия опа | F7: Б2Б - Наманган_Розия опа | G7: P2 | H7: Розия опа | I7: Эльфор р-р. для инф 5м/мл | J7: 480 | K7: 18300 | L7: 8784000 | M7: 100 | N7: =+L7*M7% -> 8784000 | O7: =L7-N7 -> 0
A8: 2025 | B8: 2 | C8: 45714 | D8: P2000000195 | E8: Рустам ака | F8: Таш.Обл_Рустам ака | G8: P2 | H8: Рустам ака Таш обл | I8: Эльфор р-р. для инф 5м/мл | J8: 1200 | K8: 18300 | L8: 21960000 | M8: 100 | N8: =+L8*M8% -> 21960000 | O8: =L8-N8 -> 0
A9: 2025 | B9: 2 | C9: 45714 | D9: P2000000196 | E9: Фотима опа | F9: Сирдарьё_Фотима опа | G9: P2 | H9: Фотима опа | I9: Эльфор р-р. для инф 5м/мл | J9: 480 | K9: 18300 | L9: 8784000 | M9: 100 | N9: =+L9*M9% -> 8784000 | O9: =L9-N9 -> 0
A10: 2025 | B10: 3 | C10: 45723 | D10: P2000000243 | E10: Сарвар ака | F10: Сурхондарьё_Сарвар ака | G10: P2 | H10: Сарвар ака | I10: Эльфор р-р. для инф 5м/мл | J10: 500 | K10: 18300 | L10: 9150000 | M10: 100 | N10: =+L10*M10% -> 9150000 | O10: =L10-N10 -> 0
A11: 2025 | B11: 4 | C11: 45768 | D11: P2000000380 | E11: Б2Б - Навоий_Гулшода опа | F11: Б2Б - Навоий_Гулшода опа | G11: P2 | H11: Б2Б - Навоий_Гулшода опа | I11: Эльфор р-р. для инф 5м/мл | J11: 240 | K11: 18300 | L11: 4392000 | M11: 100 | N11: =+L11*M11% -> 4392000 | O11: =L11-N11 -> 0
A12: 2025 | B12: 4 | C12: 45768 | D12: P2000000381 | E12: Б2Б - Наманган_Розия опа | F12: Б2Б - Наманган_Розия опа | G12: P2 | H12: Б2Б - Наманган_Розия опа | I12: Эльфор р-р. для инф 5м/мл | J12: 500 | K12: 18300 | L12: 9150000 | M12: 100 | N12: =+L12*M12% -> 9150000 | O12: =L12-N12 -> 0
A13: 2025 | B13: 4 | C13: 45768 | D13: P2000000395 | E13: Сарвар ака | F13: Сурхондарьё_Сарвар ака | G13: P2 | H13: Сарвар ака | I13: Эльфор р-р. для инф 5м/мл | J13: 600 | K13: 19000 | L13: 11400000 | M13: 100 | N13: =+L13*M13% -> 11400000 | O13: =L13-N13 -> 0
A14: 2025 | B14: 4 | C14: 45769 | D14: P2000000399 | E14: Б2Б - Хоразм_Саййора опа | F14: Б2Б - Хоразм_Саййора опа | G14: P2 | H14: Б2Б - Хоразм_Саййора опа | I14: Эльфор р-р. для инф 5м/мл | J14: 1200 | K14: 16300 | L14: 19560000 | M14: 100 | N14: =+L14*M14% -> 19560000 | O14: =L14-N14 -> 0
... A388: 2026 | B388: 5 | C388: 46157 | D388: R2000000427 | E388: Фотима опа | F388: Сирдарё_Фотима опа | G388: R2 | H388: Сирдарё_Фотима опа | I388: Эпсол раствор для инфузий 12 мг/мл 50 мл | J388: 50 | K388: 33000 | L388: 1650000 | M388: 0 | N388: =+L388*M388% -> 0 | O388: =L388-N388 -> 1650000

Sheet Продажа Переч
K1: =SUBTOTAL(9,K3:K1048576) -> 62762 | M1: =SUBTOTAL(9,M3:M1048576) -> 3.8928103e+09 | N1: =SUBTOTAL(9,N3:N1048576) -> 1263082000 | O1: 0.18 | P1: =SUBTOTAL(9,P3:P1048576) -> 1.7095572e+09 | R1: =SUBTOTAL(9,R3:R1048576) -> 3.4875598e+09 | S1: =SUBTOTAL(9,S3:S1048576) -> 4.0525045e+08
A2: Год | B2: Месяц | C2: Дата | E2: Номер СФ | F2: Медпредставитель | G2: Команда | H2: Поставщик | I2: Название организации | J2: Наименование | K2: Количество | L2: Цена | M2: Сумма | N2: Разница окр/ | O2: Зп | P2: Сумма Итого расход | Q2: Оплата | R2: Оплата сумма | S2: Остаток долга
A3: 2025 | B3: 3 | C3: 45730 | D3: =+E3&G3 -> PPS00002118Сурхондарьё_Сарвар ака | E3: PPS00002118 | F3: Сарварбек ака | G3: Сурхондарьё_Сарвар ака | H3: PPS | I3: "Nurbek Layt" Xk | J3: Эльфор р-р. для инф 5м/мл | K3: 40 | L3: 36955.08 | M3: 1478203.2 | N3: =+K3*15000 -> 600000 | O3: =+M3*$O$1 -> 266076.58 | P3: =+N3+O3 -> 866076.58 | Q3: 100 | R3: =+M3*Q3% -> 1478203.2 | S3: =M3-R3 -> 0
A4: 2025 | B4: 3 | C4: 45743 | D4: =+E4&G4 -> PPS00002496Бухоро_Рустам ака | E4: PPS00002496 | F4: Нозими опа (Бух) | G4: Бухоро_Рустам ака | H4: PPS | I4: "Diabetes Pharma" Mchj | J4: Эльфор р-р. для инф 5м/мл | K4: 120 | L4: 36955.08 | M4: 4434609.6 | N4: =+K4*15000 -> 1800000 | O4: =+M4*$O$1 -> 798229.73 | P4: =+N4+O4 -> 2598229.7 | Q4: 100 | R4: =+M4*Q4% -> 4434609.6 | S4: =M4-R4 -> 0
A5: 2025 | B5: 4 | C5: 45750 | D5: =+E5&G5 -> PPS00002647Бухоро_Рустам ака | E5: PPS00002647 | F5: Нозими опа (Бух) | G5: Бухоро_Рустам ака | H5: PPS | I5: "IBN SINO" XK | J5: Эльфор р-р. для инф 5м/мл | K5: 30 | L5: 36955.08 | M5: 1108652.4 | N5: =+K5*15000 -> 450000 | O5: =+M5*$O$1 -> 199557.43 | P5: =+N5+O5 -> 649557.43 | Q5: 100 | R5: =+M5*Q5% -> 1108652.4 | S5: =M5-R5 -> 0
A6: 2025 | B6: 4 | C6: 45751 | D6: =+E6&G6 -> PPS00002691Таш,Обл_Рустам ака | E6: PPS00002691 | F6: Рустам ака (Т.О) | G6: Таш,Обл_Рустам ака | H6: PPS | I6: "Farma Com Pro" Mchj | J6: Эльфор р-р. для инф 5м/мл | K6: 20 | L6: 36955.08 | M6: 739101.6 | N6: =+K6*15000 -> 300000 | O6: =+M6*$O$1 -> 133038.29 | P6: =+N6+O6 -> 433038.29 | Q6: 100 | R6: =+M6*Q6% -> 739101.6 | S6: =M6-R6 -> 0
A7: 2025 | B7: 4 | C7: 45772 | D7: =+E7&G7 -> PPS00003424Сурхондарьё_Сарвар ака | E7: PPS00003424 | F7: Сарварбек ака | G7: Сурхондарьё_Сарвар ака | H7: PPS | I7: Sport Plyus Xk | J7: Эльфор р-р. для инф 5м/мл | K7: 20 | L7: 36955.08 | M7: 739101.6 | N7: =+K7*15000 -> 300000 | O7: =+M7*$O$1 -> 133038.29 | P7: =+N7+O7 -> 433038.29 | Q7: 100 | R7: =+M7*Q7% -> 739101.6 | S7: =M7-R7 -> 0
A8: 2025 | B8: 4 | C8: 45776 | D8: =+E8&G8 -> PPS00003544Самарканд_Хуршед ака | E8: PPS00003544 | F8: Хуршид Ака 3 (Сам) | G8: Самарканд_Хуршед ака | H8: PPS | I8: "Star Asadbek" Mchj | J8: Эльфор р-р. для инф 5м/мл | K8: 100 | L8: 36955.08 | M8: 3695508 | N8: =+K8*15000 -> 1500000 | O8: =+M8*$O$1 -> 665191.44 | P8: =+N8+O8 -> 2165191.4 | Q8: 100 | R8: =+M8*Q8% -> 3695508 | S8: =M8-R8 -> 0
A9: 2025 | B9: 4 | C9: 45776 | D9: =+E9&G9 -> PPS00003551Сурхондарьё_Сарвар ака | E9: PPS00003551 | F9: Сарварбек ака | G9: Сурхондарьё_Сарвар ака | H9: PPS | I9: "Nurbek Layt" Xk | J9: Эльфор р-р. для инф 5м/мл | K9: 50 | L9: 36955.08 | M9: 1847754 | N9: =+K9*15000 -> 750000 | O9: =+M9*$O$1 -> 332595.72 | P9: =+N9+O9 -> 1082595.7 | Q9: 100 | R9: =+M9*Q9% -> 1847754 | S9: =M9-R9 -> 0
A10: 2025 | B10: 5 | C10: 45779 | D10: =+E10&G10 -> PPS00003627Таш,Обл_Рустам ака | E10: PPS00003627 | F10: Рустам ака (Т.О) | G10: Таш,Обл_Рустам ака | H10: PPS | I10: "Farma Com Pro" Mchj | J10: Эльфор р-р. для инф 5м/мл | K10: 42 | L10: 36955.08 | M10: 1552113.4 | N10: =+K10*15000 -> 630000 | O10: =+M10*$O$1 -> 279380.4 | P10: =+N10+O10 -> 909380.4 | Q10: 100 | R10: =+M10*Q10% -> 1552113.4 | S10: =M10-R10 -> 0
A11: 2025 | B11: 5 | C11: 45783 | D11: =+E11&G11 -> PPS00003759Бухоро_Рустам ака | E11: PPS00003759 | F11: Нозими опа (Бух) | G11: Бухоро_Рустам ака | H11: PPS | I11: "Buxoro Dori Darmon" Mchj | J11: Эльфор р-р. для инф 5м/мл | K11: 1500 | L11: 36955.08 | M11: 55432620 | N11: =+K11*15000 -> 22500000 | O11: =+M11*$O$1 -> 9977871.6 | P11: =+N11+O11 -> 32477872 | Q11: 100 | R11: =+M11*Q11% -> 55432620 | S11: =M11-R11 -> 0
A12: 2025 | B12: 5 | C12: 45783 | D12: =+E12&G12 -> PPS00003759Бухоро_Рустам ака | E12: PPS00003759 | F12: Нозими опа (Бух) | G12: Бухоро_Рустам ака | H12: PPS | I12: "Buxoro Dori Darmon" Mchj | J12: Эльфор р-р. для инф 5м/мл | K12: 1500 | L12: 36955.08 | M12: 55432620 | N12: =+K12*15000 -> 22500000 | O12: =+M12*$O$1 -> 9977871.6 | P12: =+N12+O12 -> 32477872 | Q12: 100 | R12: =+M12*Q12% -> 55432620 | S12: =M12-R12 -> 0
A13: 2025 | B13: 5 | C13: 45805 | D13: =+E13&G13 -> PPS00004467Сирдарё_Фотима опа | E13: PPS00004467 | F13: Абдушукур ака (Сир) | G13: Сирдарё_Фотима опа | H13: PPS | I13: ЧП "Aju-Biznes-Star" | J13: Эльфор р-р. для инф 5м/мл | K13: 40 | L13: 36955.08 | M13: 1478203.2 | N13: =+K13*15000 -> 600000 | O13: =+M13*$O$1 -> 266076.58 | P13: =+N13+O13 -> 866076.58 | Q13: 100 | R13: =+M13*Q13% -> 1478203.2 | S13: =M13-R13 -> 0
A14: 2025 | B14: 6 | C14: 45812 | D14: =+E14&G14 -> PPS00004665Сирдарё_Фотима опа | E14: PPS00004665 | F14: Фотима опа (Сир) | G14: Сирдарё_Фотима опа | H14: PPS | I14: MCHJ Asad Jahongir Farm | J14: Эльфор р-р. для инф 5м/мл | K14: 500 | L14: 36955.08 | M14: 18477540 | N14: =+K14*15000 -> 7500000 | O14: =+M14*$O$1 -> 3325957.2 | P14: =+N14+O14 -> 10825957 | Q14: 100 | R14: =+M14*Q14% -> 18477540 | S14: =M14-R14 -> 0
... A110: 2025 | B110: 10 | C110: 45947 | D110: =+E110&G110 -> PPS00008650Сурхондарьё_Сарвар ака | E110: PPS00008650 | F110: Сарвар ака (Срх) | G110: Сурхондарьё_Сарвар ака | H110: PPS | I110: "Sevara-Bio-Farm" Xk | J110: Эльфор р-р. для инф 5м/мл | K110: 60 | L110: 40621 | M110: 2437260 | N110: =+K110*15000 -> 900000 | O110: =+M110*$O$1 -> 438706.8 | P110: =+N110+O110 -> 1338706.8 | Q110: 100 | R110: =+M110*Q110% -> 2437260 | S110: =M110-R110 -> 0
A111: 2025 | B111: 10 | C111: 45947 | D111: =+E111&G111 -> PPS00008654Таш.Обл_Шахло опа | E111: PPS00008654 | F111: Шахло опа (Т.О) | G111: Таш.Обл_Шахло опа | H111: PPS | I111: "LIR" XK | J111: Софин раствор для инфузий 5% 100 мл | K111: 40 | L111: 120000 | M111: 4800000 | N111: =+K111*35000 -> 1400000 | O111: =+M111*$O$1 -> 864000 | P111: =+N111+O111 -> 2264000 | Q111: 100 | R111: =+M111*Q111% -> 4800000 | S111: =M111-R111 -> 0
A112: 2025 | B112: 10 | C112: 45950 | D112: =+E112&G112 -> PPS00008704Навоий_Дильноза опа | E112: PPS00008704 | F112: Рано опа (Нав) | G112: Навоий_Дильноза опа | H112: PPS | I112: "Grand-Medikal Center" Mchj | J112: Эльфор р-р. для инф 5м/мл | K112: 100 | L112: 40621 | M112: 4062100 | N112: =+K112*15000 -> 1500000 | O112: =+M112*$O$1 -> 731178 | P112: =+N112+O112 -> 2231178 | Q112: 100 | R112: =+M112*Q112% -> 4062100 | S112: =M112-R112 -> 0
A113: 2025 | B113: 10 | C113: 45950 | D113: =+E113&G113 -> PPS00008717Навоий_Дильноза опа | E113: PPS00008717 | F113: Рано опа (Нав) | G113: Навоий_Дильноза опа | H113: PPS | I113: "Navoiy Ultra Diagnostika" Mchj | J113: Эльфор р-р. для инф 5м/мл | K113: 25 | L113: 40621 | M113: 1015525 | N113: =+K113*15000 -> 375000 | O113: =+M113*$O$1 -> 182794.5 | P113: =+N113+O113 -> 557794.5 | Q113: 100 | R113: =+M113*Q113% -> 1015525 | S113: =M113-R113 -> 0
A114: 2025 | B114: 10 | C114: 45950 | D114: =+E114&G114 -> PPS00008738Тошкент_Мохира опа | E114: PPS00008738 | F114: Камола опа (Тош) | G114: Тошкент_Мохира опа | H114: PPS | I114: "Pharzam Pharm" Mchj | J114: Эльфор р-р. для инф 5м/мл | K114: 50 | L114: 40621 | M114: 2031050 | N114: =+K114*15000 -> 750000 | O114: =+M114*$O$1 -> 365589 | P114: =+N114+O114 -> 1115589 | Q114: 100 | R114: =+M114*Q114% -> 2031050 | S114: =M114-R114 -> 0
A115: 2025 | B115: 10 | C115: 45951 | D115: =+E115&G115 -> PPS00008752Тошкент_Мохира опа | E115: PPS00008752 | F115: Дурдона опа (Тош) | G115: Тошкент_Мохира опа | H115: PPS | I115: "Super Pharm" Mchj | J115: Эльфор р-р. для инф 5м/мл | K115: 50 | L115: 40621 | M115: 2031050 | N115: =+K115*15000 -> 750000 | O115: =+M115*$O$1 -> 365589 | P115: =+N115+O115 -> 1115589 | Q115: 100 | R115: =+M115*Q115% -> 2031050 | S115: =M115-R115 -> 0
A116: 2025 | B116: 10 | C116: 45951 | D116: =+E116&G116 -> PPS00008769Шахрисабз_Мафтуна опа | E116: PPS00008769 | F116: Чарос опа (Шах) | G116: Шахрисабз_Мафтуна опа | H116: PPS | I116: "TURDI RASULOVICH" XK | J116: Софин раствор для инфузий 5% 100 мл | K116: 100 | L116: 120000 | M116: 12000000 | N116: =+K116*35000 -> 3500000 | O116: =+M116*$O$1 -> 2160000 | P116: =+N116+O116 -> 5660000 | Q116: 100 | R116: =+M116*Q116% -> 12000000 | S116: =M116-R116 -> 0
A117: 2025 | B117: 10 | C117: 45951 | D117: =+E117&G117 -> PPS00008784Таш.Обл_Шахло опа | E117: PPS00008784 | F117: Шахло опа (Т.О) | G117: Таш.Обл_Шахло опа | H117: PPS | I117: ООО "Lukmoni-Xakim" | J117: Софин раствор для инфузий 5% 100 мл | K117: 20 | L117: 120000 | M117: 2400000 | N117: =+K117*35000 -> 700000 | O117: =+M117*$O$1 -> 432000 | P117: =+N117+O117 -> 1132000 | Q117: 100 | R117: =+M117*Q117% -> 2400000 | S117: =M117-R117 -> 0
A118: 2025 | B118: 10 | C118: 45953 | D118: =+E118&G118 -> PPS00008836Жиззах_Саодат опа | E118: PPS00008836 | F118: Дилноза опа (Жиз) | G118: Жиззах_Саодат опа | H118: PPS | I118: "Omad Sahovat Farm" Xk | J118: Эльфор р-р. для инф 5м/мл | K118: 30 | L118: 40621 | M118: 1218630 | N118: =+K118*15000 -> 450000 | O118: =+M118*$O$1 -> 219353.4 | P118: =+N118+O118 -> 669353.4 | Q118: 100 | R118: =+M118*Q118% -> 1218630 | S118: =M118-R118 -> 0
A119: 2025 | B119: 10 | C119: 45953 | D119: =+E119&G119 -> PPS00008867Самарканд_Хуршед ака | E119: PPS00008867 | F119: Хуршид Ака 3 (Сам) | G119: Самарканд_Хуршед ака | H119: PPS | I119: "Benevitta" Mchj | J119: Софин раствор для инфузий 5% 100 мл | K119: 120 | L119: 120000 | M119: 14400000 | N119: =+K119*35000 -> 4200000 | O119: =+M119*$O$1 -> 2592000 | P119: =+N119+O119 -> 6792000 | Q119: 100 | R119: =+M119*Q119% -> 14400000 | S119: =M119-R119 -> 0
A120: 2025 | B120: 10 | C120: 45953 | D120: =+E120&G120 -> PPS00008871Жиззах_Саодат опа | E120: PPS00008871 | F120: Дилноза опа (Жиз) | G120: Жиззах_Саодат опа | H120: PPS | I120: "Akobir Pharm 444" Mchj | J120: Эльфор р-р. для инф 5м/мл | K120: 48 | L120: 40621 | M120: 1949808 | N120: =+K120*15000 -> 720000 | O120: =+M120*$O$1 -> 350965.44 | P120: =+N120+O120 -> 1070965.4 | Q120: 100 | R120: =+M120*Q120% -> 1949808 | S120: =M120-R120 -> 0
A121: 2025 | B121: 10 | C121: 45953 | D121: =+E121&G121 -> PPS00008884Жиззах_Саодат опа | E121: PPS00008884 | F121: Дилноза опа (Жиз) | G121: Жиззах_Саодат опа | H121: PPS | I121: "Shaxizodaa Med" Xk | J121: Эльфор р-р. для инф 5м/мл | K121: 10 | L121: 40621 | M121: 406210 | N121: =+K121*15000 -> 150000 | O121: =+M121*$O$1 -> 73117.8 | P121: =+N121+O121 -> 223117.8 | Q121: 100 | R121: =+M121*Q121% -> 406210 | S121: =M121-R121 -> 0
A122: 2025 | B122: 10 | C122: 45954 | D122: =+E122&G122 -> PPS00008904Тошкент_Мохира опа | E122: PPS00008904 | F122: Нигора опа (Тош) | G122: Тошкент_Мохира опа | H122: PPS | I122: "Proxima" Xk | J122: Эльфор р-р. для инф 5м/мл | K122: 50 | L122: 40621 | M122: 2031050 | N122: =+K122*15000 -> 750000 | O122: =+M122*$O$1 -> 365589 | P122: =+N122+O122 -> 1115589 | Q122: 100 | R122: =+M122*Q122% -> 2031050 | S122: =M122-R122 -> 0
A123: 2025 | B123: 10 | C123: 45954 | D123: =+E123&G123 -> PPS00008908Сирдарё_Фотима опа | E123: PPS00008908 | F123: Абдушукур ака (Сир) | G123: Сирдарё_Фотима опа | H123: PPS | I123: "Baxtiyor Turg'unovich" Ktxf | J123: Эльфор р-р. для инф 5м/мл | K123: 100 | L123: 40621 | M123: 4062100 | N123: =+K123*15000 -> 1500000 | O123: =+M123*$O$1 -> 731178 | P123: =+N123+O123 -> 2231178 | Q123: 100 | R123: =+M123*Q123% -> 4062100 | S123: =M123-R123 -> 0
A124: 2025 | B124: 10 | C124: 45957 | D124: =+E124&G124 -> PPS00008922Таш.Обл_Шахло опа | E124: PPS00008922 | F124: Шерзод ака (Т.О) | G124: Таш.Обл_Шахло опа | H124: PPS | I124: "111 Tabletok" Mchj | J124: Софин раствор для инфузий 5% 100 мл | K124: 20 | L124: 120000 | M124: 2400000 | N124: =+K124*35000 -> 700000 | O124: =+M124*$O$1 -> 432000 | P124: =+N124+O124 -> 1132000 | Q124: 100 | R124: =+M124*Q124% -> 2400000 | S124: =M124-R124 -> 0
A125: 2025 | B125: 10 | C125: 45957 | D125: =+E125&G125 -> PPS00008952Сирдарё_Фотима опа | E125: PPS00008952 | F125: Абдушукур ака (Сир) | G125: Сирдарё_Фотима опа | H125: PPS | I125: "Rayim Farm Invest" Mchj | J125: Эльфор р-р. для инф 5м/мл | K125: 30 | L125: 40621 | M125: 1218630 | N125: =+K125*15000 -> 450000 | O125: =+M125*$O$1 -> 219353.4 | P125: =+N125+O125 -> 669353.4 | Q125: 100 | R125: =+M125*Q125% -> 1218630 | S125: =M125-R125 -> 0
A126: 2025 | B126: 10 | C126: 45958 | D126: =+E126&G126 -> PPS00009008Сирдарё_Фотима опа | E126: PPS00009008 | F126: Абдушукур ака (Сир) | G126: Сирдарё_Фотима опа | H126: PPS | I126: "Shifobaxsh" Xk | J126: Эльфор р-р. для инф 5м/мл | K126: 50 | L126: 40621 | M126: 2031050 | N126: =+K126*15000 -> 750000 | O126: =+M126*$O$1 -> 365589 | P126: =+N126+O126 -> 1115589 | Q126: 100 | R126: =+M126*Q126% -> 2031050 | S126: =M126-R126 -> 0
A127: 2025 | B127: 10 | C127: 45960 | D127: =+E127&G127 -> PPS00009066Навоий_Дильноза опа | E127: PPS00009066 | F127: Рано опа (Нав) | G127: Навоий_Дильноза опа | H127: PPS | I127: "XUJAI-JAXON GRAND" MChJ | J127: Эльфор р-р. для инф 5м/мл | K127: 50 | L127: 40621 | M127: 2031050 | N127: =+K127*15000 -> 750000 | O127: =+M127*$O$1 -> 365589 | P127: =+N127+O127 -> 1115589 | Q127: 100 | R127: =+M127*Q127% -> 2031050 | S127: =M127-R127 -> 0
A128: 2025 | B128: 10 | C128: 45960 | D128: =+E128&G128 -> PPS00009069Жиззах_Саодат опа | E128: PPS00009069 | F128: Жавлон ака (Жиз) | G128: Жиззах_Саодат опа | H128: PPS | I128: "Usta Maxmud"Xk | J128: Эльфор р-р. для инф 5м/мл | K128: 48 | L128: 40621 | M128: 1949808 | N128: =+K128*15000 -> 720000 | O128: =+M128*$O$1 -> 350965.44 | P128: =+N128+O128 -> 1070965.4 | Q128: 100 | R128: =+M128*Q128% -> 1949808 | S128: =M128-R128 -> 0
A129: 2025 | B129: 11 | C129: 45964 | D129: =+E129&G129 -> PPS00009173Таш.Обл_Шахло опа | E129: PPS00009173 | F129: Шерзод ака (Т.О) | G129: Таш.Обл_Шахло опа | H129: PPS | I129: "ASROR-ShIFOKOR" XK | J129: Софин раствор для инфузий 5% 100 мл | K129: 10 | L129: 120000 | M129: 1200000 | N129: =+K129*35000 -> 350000 | O129: =+M129*$O$1 -> 216000 | P129: =+N129+O129 -> 566000 | Q129: 100 | R129: =+M129*Q129% -> 1200000 | S129: =M129-R129 -> 0
A130: 2025 | B130: 11 | C130: 45964 | D130: =+E130&G130 -> PPS00009175Сирдарё_Фотима опа | E130: PPS00009175 | F130: Абдушукур ака (Сир) | G130: Сирдарё_Фотима опа | H130: PPS | I130: ООО "Shodlik-Mc" | J130: Эльфор р-р. для инф 5м/мл | K130: 200 | L130: 40621 | M130: 8124200 | N130: =+K130*15000 -> 3000000 | O130: =+M130*$O$1 -> 1462356 | P130: =+N130+O130 -> 4462356 | Q130: 100 | R130: =+M130*Q130% -> 8124200 | S130: =M130-R130 -> 0
A131: 2025 | B131: 11 | C131: 45965 | D131: =+E131&G131 -> PPS00009249Кашкадарьё_Феруз ака | E131: PPS00009249 | F131: Шахноза опа (Кшд) | G131: Кашкадарьё_Феруз ака | H131: PPS | I131: ЧП "Malxam-Fayz-Dilxush " | J131: Эпсол раствор для инфузий 12 мг/мл 50 мл | K131: 10 | L131: 65000 | M131: 650000 | N131: =+K131*20000 -> 200000 | O131: =+M131*$O$1 -> 117000 | P131: =+N131+O131 -> 317000 | Q131: 100 | R131: =+M131*Q131% -> 650000 | S131: =M131-R131 -> 0
A132: 2025 | B132: 11 | C132: 45965 | D132: =+E132&G132 -> PPS00009253Навоий_Дильноза опа | E132: PPS00009253 | F132: Рано опа (Нав) | G132: Навоий_Дильноза опа | H132: PPS | I132: "Grand-Medikal Center" Mchj | J132: Эльфор р-р. для инф 5м/мл | K132: 48 | L132: 40621 | M132: 1949808 | N132: =+K132*15000 -> 720000 | O132: =+M132*$O$1 -> 350965.44 | P132: =+N132+O132 -> 1070965.4 | Q132: 100 | R132: =+M132*Q132% -> 1949808 | S132: =M132-R132 -> 0
A133: 2025 | B133: 11 | C133: 45966 | D133: =+E133&G133 -> PPS00009323Тошкент_Мохира опа | E133: PPS00009323 | F133: Нигора опа (Тош) | G133: Тошкент_Мохира опа | H133: PPS | I133: "Mmm-Apteka" Mchj | J133: Эльфор р-р. для инф 5м/мл | K133: 30 | L133: 40621 | M133: 1218630 | N133: =+K133*15000 -> 450000 | O133: =+M133*$O$1 -> 219353.4 | P133: =+N133+O133 -> 669353.4 | Q133: 100 | R133: =+M133*Q133% -> 1218630 | S133: =M133-R133 -> 0
A134: 2025 | B134: 11 | C134: 45967 | D134: =+E134&G134 -> PPS00009329Жиззах_Саодат опа | E134: PPS00009329 | F134: Дилноза опа (Жиз) | G134: Жиззах_Саодат опа | H134: PPS | I134: "Omad Sahovat Farm" Xk | J134: Эльфор р-р. для инф 5м/мл | K134: 20 | L134: 40621 | M134: 812420 | N134: =+K134*15000 -> 300000 | O134: =+M134*$O$1 -> 146235.6 | P134: =+N134+O134 -> 446235.6 | Q134: 100 | R134: =+M134*Q134% -> 812420 | S134: =M134-R134 -> 0
A135: 2025 | B135: 11 | C135: 45968 | D135: =+E135&G135 -> PPS00009388Кашкадарьё_Феруз ака | E135: PPS00009388 | F135: Шахноза опа (Кшд) | G135: Кашкадарьё_Феруз ака | H135: PPS | I135: "Feru-Za Pharm" Xk | J135: Эпсол раствор для инфузий 12 мг/мл 50 мл | K135: 20 | L135: 65000 | M135: 1300000 | N135: =+K135*20000 -> 400000 | O135: =+M135*$O$1 -> 234000 | P135: =+N135+O135 -> 634000 | Q135: 100 | R135: =+M135*Q135% -> 1300000 | S135: =M135-R135 -> 0
A136: 2025 | B136: 11 | C136: 45968 | D136: =+E136&G136 -> PPS00009396Таш.Обл_Шахло опа | E136: PPS00009396 | F136: Шерзод ака (Т.О) | G136: Таш.Обл_Шахло опа | H136: PPS | I136: ООО "Lukmoni-Xakim" | J136: Софин раствор для инфузий 5% 100 мл | K136: 50 | L136: 120000 | M136: 6000000 | N136: =+K136*35000 -> 1750000 | O136: =+M136*$O$1 -> 1080000 | P136: =+N136+O136 -> 2830000 | Q136: 100 | R136: =+M136*Q136% -> 6000000 | S136: =M136-R136 -> 0
A137: 2025 | B137: 11 | C137: 45971 | D137: =+E137&G137 -> PPS00009460Жиззах_Саодат опа | E137: PPS00009460 | F137: Жавлон ака (Жиз) | G137: Жиззах_Саодат опа | H137: PPS | I137: SUNISTAR FARM | J137: Эльфор р-р. для инф 5м/мл | K137: 50 | L137: 40621 | M137: 2031050 | N137: =+K137*15000 -> 750000 | O137: =+M137*$O$1 -> 365589 | P137: =+N137+O137 -> 1115589 | Q137: 100 | R137: =+M137*Q137% -> 2031050 | S137: =M137-R137 -> 0
A138: 2025 | B138: 11 | C138: 45972 | D138: =+E138&G138 -> PPS00009474Навоий_Дильноза опа | E138: PPS00009474 | F138: Рано опа (Нав) | G138: Навоий_Дильноза опа | H138: PPS | I138: "NAVOIY BINAFSHA" XK | J138: Эльфор р-р. для инф 5м/мл | K138: 48 | L138: 40621 | M138: 1949808 | N138: =+K138*15000 -> 720000 | O138: =+M138*$O$1 -> 350965.44 | P138: =+N138+O138 -> 1070965.4 | Q138: 100 | R138: =+M138*Q138% -> 1949808 | S138: =M138-R138 -> 0
A139: 2025 | B139: 11 | C139: 45972 | D139: =+E139&G139 -> PPS00009501Сирдарё_Фотима опа | E139: PPS00009501 | F139: Фотима опа (Сир) | G139: Сирдарё_Фотима опа | H139: PPS | I139: "Shifobaxsh" Xk | J139: Эльфор р-р. для инф 5м/мл | K139: 50 | L139: 40621 | M139: 2031050 | N139: =+K139*15000 -> 750000 | O139: =+M139*$O$1 -> 365589 | P139: =+N139+O139 -> 1115589 | Q139: 100 | R139: =+M139*Q139% -> 2031050 | S139: =M139-R139 -> 0
A140: 2025 | B140: 11 | C140: 45972 | D140: =+E140&G140 -> PPS00009503Таш,Обл_Рустам ака | E140: PPS00009503 | F140: Рустам ака (Т.О) | G140: Таш,Обл_Рустам ака | H140: PPS | I140: "FARTUNA-RAMZ-FARM" MChJ | J140: Эльфор р-р. для инф 5м/мл | K140: 10 | L140: 40621 | M140: 406210 | N140: =+K140*15000 -> 150000 | O140: =+M140*$O$1 -> 73117.8 | P140: =+N140+O140 -> 223117.8 | Q140: 100 | R140: =+M140*Q140% -> 406210 | S140: =M140-R140 -> 0
A141: 2025 | B141: 11 | C141: 45972 | D141: =+E141&G141 -> PPS00009510Таш.Обл_Шахло опа | E141: PPS00009510 | F141: Шахло опа (Т.О) | G141: Таш.Обл_Шахло опа | H141: PPS | I141: "FERUZ PHARM-SERVICE" MChJ | J141: Софин раствор для инфузий 5% 100 мл | K141: 10 | L141: 120000 | M141: 1200000 | N141: =+K141*35000 -> 350000 | O141: =+M141*$O$1 -> 216000 | P141: =+N141+O141 -> 566000 | Q141: 100 | R141: =+M141*Q141% -> 1200000 | S141: =M141-R141 -> 0
A142: 2025 | B142: 11 | C142: 45972 | D142: =+E142&G142 -> PPS00009519Кашкадарьё_Феруз ака | E142: PPS00009519 | F142: Шахноза опа (Кшд) | G142: Кашкадарьё_Феруз ака | H142: PPS | I142: "AL NASAFIY KAFOLAT FARM" MChJ | J142: Эпсол раствор для инфузий 12 мг/мл 50 мл | K142: 20 | L142: 65000 | M142: 1300000 | N142: =+K142*20000 -> 400000 | O142: =+M142*$O$1 -> 234000 | P142: =+N142+O142 -> 634000 | Q142: 100 | R142: =+M142*Q142% -> 1300000 | S142: =M142-R142 -> 0
A143: 2025 | B143: 11 | C143: 45972 | D143: =+E143&G143 -> PPS00009523Кашкадарьё_Феруз ака | E143: PPS00009523 | F143: Шахноза опа (Кшд) | G143: Кашкадарьё_Феруз ака | H143: PPS | I143: "Gullola Media Farm" Xk | J143: Эпсол раствор для инфузий 12 мг/мл 50 мл | K143: 10 | L143: 65000 | M143: 650000 | N143: =+K143*20000 -> 200000 | O143: =+M143*$O$1 -> 117000 | P143: =+N143+O143 -> 317000 | Q143: 100 | R143: =+M143*Q143% -> 650000 | S143: =M143-R143 -> 0
A144: 2025 | B144: 11 | C144: 45972 | D144: =+E144&G144 -> PPS00009525Кашкадарьё_Феруз ака | E144: PPS00009525 | F144: Шахноза опа (Кшд) | G144: Кашкадарьё_Феруз ака | H144: PPS | I144: "Mitti Farm Med Servis" Mchj | J144: Эпсол раствор для инфузий 12 мг/мл 50 мл | K144: 20 | L144: 65000 | M144: 1300000 | N144: =+K144*20000 -> 400000 | O144: =+M144*$O$1 -> 234000 | P144: =+N144+O144 -> 634000 | Q144: 100 | R144: =+M144*Q144% -> 1300000 | S144: =M144-R144 -> 0
A145: 2025 | B145: 11 | C145: 45973 | D145: =+E145&G145 -> PPS00009551Сирдарё_Фотима опа | E145: PPS00009551 | F145: Фотима опа (Сир) | G145: Сирдарё_Фотима опа | H145: PPS | I145: ООО "Behzod-Farm-Yangiyer" | J145: Эльфор р-р. для инф 5м/мл | K145: 50 | L145: 40621 | M145: 2031050 | N145: =+K145*15000 -> 750000 | O145: =+M145*$O$1 -> 365589 | P145: =+N145+O145 -> 1115589 | Q145: 100 | R145: =+M145*Q145% -> 2031050 | S145: =M145-R145 -> 0
A146: 2025 | B146: 11 | C146: 45973 | D146: =+E146&G146 -> PPS00009559Навоий_Дильноза опа | E146: PPS00009559 | F146: Рано опа (Нав) | G146: Навоий_Дильноза опа | H146: PPS | I146: "Faxriddin-Farm Navoiy" Xk | J146: Эльфор р-р. для инф 5м/мл | K146: 30 | L146: 40621 | M146: 1218630 | N146: =+K146*15000 -> 450000 | O146: =+M146*$O$1 -> 219353.4 | P146: =+N146+O146 -> 669353.4 | Q146: 100 | R146: =+M146*Q146% -> 1218630 | S146: =M146-R146 -> 0
A147: 2025 | B147: 11 | C147: 45974 | D147: =+E147&G147 -> PPS00009593Навоий_Дильноза опа | E147: PPS00009593 | F147: Рано опа (Нав) | G147: Навоий_Дильноза опа | H147: PPS | I147: "FITO-FARM-LEK" MChJ | J147: Эльфор р-р. для инф 5м/мл | K147: 39 | L147: 40621 | M147: 1584219 | N147: =+K147*15000 -> 585000 | O147: =+M147*$O$1 -> 285159.42 | P147: =+N147+O147 -> 870159.42 | Q147: 100 | R147: =+M147*Q147% -> 1584219 | S147: =M147-R147 -> 0
A148: 2025 | B148: 11 | C148: 45974 | D148: =+E148&G148 -> PPS00009598Жиззах_Саодат опа | E148: PPS00009598 | F148: Дилноза опа (Жиз) | G148: Жиззах_Саодат опа | H148: PPS | I148: "Usta Maxmud"Xk | J148: Эльфор р-р. для инф 5м/мл | K148: 70 | L148: 40621 | M148: 2843470 | N148: =+K148*15000 -> 1050000 | O148: =+M148*$O$1 -> 511824.6 | P148: =+N148+O148 -> 1561824.6 | Q148: 100 | R148: =+M148*Q148% -> 2843470 | S148: =M148-R148 -> 0
A149: 2025 | B149: 11 | C149: 45975 | D149: =+E149&G149 -> PPS00009638Таш.Обл_Шахло опа | E149: PPS00009638 | F149: Шерзод ака (Т.О) | G149: Таш.Обл_Шахло опа | H149: PPS | I149: "PLATINUM OPTIMA SERVICE" MChJ | J149: Софин раствор для инфузий 5% 100 мл | K149: 20 | L149: 120000 | M149: 2400000 | N149: =+K149*35000 -> 700000 | O149: =+M149*$O$1 -> 432000 | P149: =+N149+O149 -> 1132000 | Q149: 100 | R149: =+M149*Q149% -> 2400000 | S149: =M149-R149 -> 0
A150: 2025 | B150: 11 | C150: 45975 | D150: =+E150&G150 -> PPS00009639Сирдарё_Фотима опа | E150: PPS00009639 | F150: Фотима опа (Сир) | G150: Сирдарё_Фотима опа | H150: PPS | I150: "Soliboy Biznes Hamkor" Mchj | J150: Эльфор р-р. для инф 5м/мл | K150: 100 | L150: 40621 | M150: 4062100 | N150: =+K150*15000 -> 1500000 | O150: =+M150*$O$1 -> 731178 | P150: =+N150+O150 -> 2231178 | Q150: 100 | R150: =+M150*Q150% -> 4062100 | S150: =M150-R150 -> 0
A151: 2025 | B151: 11 | C151: 45975 | D151: =+E151&G151 -> PPS00009645Навоий_Дильноза опа | E151: PPS00009645 | F151: Рано опа (Нав) | G151: Навоий_Дильноза опа | H151: PPS | I151: "Navoiy Ultra Diagnostika" Mchj | J151: Эльфор р-р. для инф 5м/мл | K151: 20 | L151: 40621 | M151: 812420 | N151: =+K151*15000 -> 300000 | O151: =+M151*$O$1 -> 146235.6 | P151: =+N151+O151 -> 446235.6 | Q151: 100 | R151: =+M151*Q151% -> 812420 | S151: =M151-R151 -> 0
A152: 2025 | B152: 11 | C152: 45975 | D152: =+E152&G152 -> PPS00009660Шахрисабз_Мафтуна опа | E152: PPS00009660 | F152: Чарос опа (Шах) | G152: Шахрисабз_Мафтуна опа | H152: PPS | I152: "Jasmin-Farangiz" Xk | J152: Софин раствор для инфузий 5% 100 мл | K152: 3 | L152: 120000 | M152: 360000 | N152: =+K152*35000 -> 105000 | O152: =+M152*$O$1 -> 64800 | P152: =+N152+O152 -> 169800 | Q152: 100 | R152: =+M152*Q152% -> 360000 | S152: =M152-R152 -> 0
A153: 2025 | B153: 11 | C153: 45978 | D153: =+E153&G153 -> PPS00009664Навоий_Дильноза опа | E153: PPS00009664 | F153: Рано опа (Нав) | G153: Навоий_Дильноза опа | H153: PPS | I153: "Sof Dori Farm" Mchj | J153: Эльфор р-р. для инф 5м/мл | K153: 33 | L153: 40621 | M153: 1340493 | N153: =+K153*15000 -> 495000 | O153: =+M153*$O$1 -> 241288.74 | P153: =+N153+O153 -> 736288.74 | Q153: 100 | R153: =+M153*Q153% -> 1340493 | S153: =M153-R153 -> 0
A154: 2025 | B154: 11 | C154: 45978 | D154: =+E154&G154 -> PPS00009670Жиззах_Саодат опа | E154: PPS00009670 | F154: Жавлон ака (Жиз) | G154: Жиззах_Саодат опа | H154: PPS | I154: MCHJ Saxob-Uchqun Farm | J154: Эльфор р-р. для инф 5м/мл | K154: 60 | L154: 40621 | M154: 2437260 | N154: =+K154*15000 -> 900000 | O154: =+M154*$O$1 -> 438706.8 | P154: =+N154+O154 -> 1338706.8 | Q154: 100 | R154: =+M154*Q154% -> 2437260 | S154: =M154-R154 -> 0
A155: 2025 | B155: 11 | C155: 45978 | D155: =+E155&G155 -> PPS00009688Жиззах_Саодат опа | E155: PPS00009688 | F155: Дилноза опа (Жиз) | G155: Жиззах_Саодат опа | H155: PPS | I155: "Malxam-2" Xk | J155: Эльфор р-р. для инф 5м/мл | K155: 10 | L155: 40621 | M155: 406210 | N155: =+K155*15000 -> 150000 | O155: =+M155*$O$1 -> 73117.8 | P155: =+N155+O155 -> 223117.8 | Q155: 100 | R155: =+M155*Q155% -> 406210 | S155: =M155-R155 -> 0
A156: 2025 | B156: 11 | C156: 45978 | D156: =+E156&G156 -> PPS00009717Сирдарё_Фотима опа | E156: PPS00009717 | F156: Хилола опа (Сир) | G156: Сирдарё_Фотима опа | H156: PPS | I156: "RUSTAMBEK-J.B.B" XK | J156: Эльфор р-р. для инф 5м/мл | K156: 30 | L156: 40621 | M156: 1218630 | N156: =+K156*15000 -> 450000 | O156: =+M156*$O$1 -> 219353.4 | P156: =+N156+O156 -> 669353.4 | Q156: 100 | R156: =+M156*Q156% -> 1218630 | S156: =M156-R156 -> 0
A157: 2025 | B157: 11 | C157: 45978 | D157: =+E157&G157 -> PPS00009728Жиззах_Саодат опа | E157: PPS00009728 | F157: Дилноза опа (Жиз) | G157: Жиззах_Саодат опа | H157: PPS | I157: "Antidard Pharm" Mchj | J157: Эльфор р-р. для инф 5м/мл | K157: 10 | L157: 40621 | M157: 406210 | N157: =+K157*15000 -> 150000 | O157: =+M157*$O$1 -> 73117.8 | P157: =+N157+O157 -> 223117.8 | Q157: 100 | R157: =+M157*Q157% -> 406210 | S157: =M157-R157 -> 0
A158: 2025 | B158: 11 | C158: 45978 | D158: =+E158&G158 -> PPS00009732Сурхондарьё_Сарвар ака | E158: PPS00009732 | F158: Сарвар ака (Срх) | G158: Сурхондарьё_Сарвар ака | H158: PPS | I158: "Ugiloy Farm" Xk | J158: Эльфор р-р. для инф 5м/мл | K158: 60 | L158: 40621 | M158: 2437260 | N158: =+K158*15000 -> 900000 | O158: =+M158*$O$1 -> 438706.8 | P158: =+N158+O158 -> 1338706.8 | Q158: 100 | R158: =+M158*Q158% -> 2437260 | S158: =M158-R158 -> 0
A159: 2025 | B159: 11 | C159: 45979 | D159: =+E159&G159 -> PPS00009773Сирдарё_Фотима опа | E159: PPS00009773 | F159: Хилола опа (Сир) | G159: Сирдарё_Фотима опа | H159: PPS | I159: "Yaqin Pharm" Mchj | J159: Эльфор р-р. для инф 5м/мл | K159: 50 | L159: 40621 | M159: 2031050 | N159: =+K159*15000 -> 750000 | O159: =+M159*$O$1 -> 365589 | P159: =+N159+O159 -> 1115589 | Q159: 100 | R159: =+M159*Q159% -> 2031050 | S159: =M159-R159 -> 0
A160: 2025 | B160: 11 | C160: 45979 | D160: =+E160&G160 -> PPS00009789Таш.Обл_Шахло опа | E160: PPS00009789 | F160: Сардор ака (Т.О) | G160: Таш.Обл_Шахло опа | H160: PPS | I160: "TO'YTEPA MED FARM" MChJ | J160: Софин раствор для инфузий 5% 100 мл | K160: 10 | L160: 120000 | M160: 1200000 | N160: =+K160*35000 -> 350000 | O160: =+M160*$O$1 -> 216000 | P160: =+N160+O160 -> 566000 | Q160: 100 | R160: =+M160*Q160% -> 1200000 | S160: =M160-R160 -> 0
A161: 2025 | B161: 11 | C161: 45979 | D161: =+E161&G161 -> PPS00009798Навоий_Дильноза опа | E161: PPS00009798 | F161: Рано опа (Нав) | G161: Навоий_Дильноза опа | H161: PPS | I161: "Grand-Medikal Center" Mchj | J161: Эльфор р-р. для инф 5м/мл | K161: 120 | L161: 40621 | M161: 4874520 | N161: =+K161*15000 -> 1800000 | O161: =+M161*$O$1 -> 877413.6 | P161: =+N161+O161 -> 2677413.6 | Q161: 100 | R161: =+M161*Q161% -> 4874520 | S161: =M161-R161 -> 0
A162: 2025 | B162: 11 | C162: 45981 | D162: =+E162&G162 -> PPS00009856Жиззах_Саодат опа | E162: PPS00009856 | F162: Дилноза опа (Жиз) | G162: Жиззах_Саодат опа | H162: PPS | I162: "Usta Maxmud"Xk | J162: Эльфор р-р. для инф 5м/мл | K162: 70 | L162: 40621 | M162: 2843470 | N162: =+K162*15000 -> 1050000 | O162: =+M162*$O$1 -> 511824.6 | P162: =+N162+O162 -> 1561824.6 | Q162: 100 | R162: =+M162*Q162% -> 2843470 | S162: =M162-R162 -> 0
A163: 2025 | B163: 11 | C163: 45981 | D163: =+E163&G163 -> PPS00009880Кашкадарьё_Феруз ака | E163: PPS00009880 | F163: Шахноза опа (Кшд) | G163: Кашкадарьё_Феруз ака | H163: PPS | I163: ЧП "Malxam-Fayz-Dilxush " | J163: Эпсол раствор для инфузий 12 мг/мл 50 мл | K163: 20 | L163: 65000 | M163: 1300000 | N163: =+K163*20000 -> 400000 | O163: =+M163*$O$1 -> 234000 | P163: =+N163+O163 -> 634000 | Q163: 100 | R163: =+M163*Q163% -> 1300000 | S163: =M163-R163 -> 0
A164: 2025 | B164: 11 | C164: 45981 | D164: =+E164&G164 -> PPS00009896Навоий_Дильноза опа | E164: PPS00009896 | F164: Дилноза опа (Нав) | G164: Навоий_Дильноза опа | H164: PPS | I164: "Azizjon Gulruxxon" Xk | J164: Эльфор р-р. для инф 5м/мл | K164: 30 | L164: 40621 | M164: 1218630 | N164: =+K164*15000 -> 450000 | O164: =+M164*$O$1 -> 219353.4 | P164: =+N164+O164 -> 669353.4 | Q164: 100 | R164: =+M164*Q164% -> 1218630 | S164: =M164-R164 -> 0
A165: 2025 | B165: 11 | C165: 45981 | D165: =+E165&G165 -> PPS00009899Тошкент_Мохира опа | E165: PPS00009899 | F165: Лобархон опа (Тош) | G165: Тошкент_Мохира опа | H165: PPS | I165: "Ko‘k-Saroy N A Hospital" Mchj | J165: Эльфор р-р. для инф 5м/мл | K165: 96 | L165: 40621 | M165: 3899616 | N165: =+K165*15000 -> 1440000 | O165: =+M165*$O$1 -> 701930.88 | P165: =+N165+O165 -> 2141930.9 | Q165: 100 | R165: =+M165*Q165% -> 3899616 | S165: =M165-R165 -> 0
A166: 2025 | B166: 11 | C166: 45981 | D166: =+E166&G166 -> PPS00009900Сирдарё_Фотима опа | E166: PPS00009900 | F166: Хилола опа (Сир) | G166: Сирдарё_Фотима опа | H166: PPS | I166: MCHJ Askarbinka Vitaminka | J166: Эльфор р-р. для инф 5м/мл | K166: 50 | L166: 40621 | M166: 2031050 | N166: =+K166*15000 -> 750000 | O166: =+M166*$O$1 -> 365589 | P166: =+N166+O166 -> 1115589 | Q166: 100 | R166: =+M166*Q166% -> 2031050 | S166: =M166-R166 -> 0
A167: 2025 | B167: 11 | C167: 45981 | D167: =+E167&G167 -> PPS00009914Навоий_Дильноза опа | E167: PPS00009914 | F167: Рано опа (Нав) | G167: Навоий_Дильноза опа | H167: PPS | I167: "Nurvita Pharm" Mchj | J167: Эльфор р-р. для инф 5м/мл | K167: 30 | L167: 40621 | M167: 1218630 | N167: =+K167*15000 -> 450000 | O167: =+M167*$O$1 -> 219353.4 | P167: =+N167+O167 -> 669353.4 | Q167: 100 | R167: =+M167*Q167% -> 1218630 | S167: =M167-R167 -> 0
A168: 2025 | B168: 11 | C168: 45981 | D168: =+E168&G168 -> PPS00009917Навоий_Дильноза опа | E168: PPS00009917 | F168: Рано опа (Нав) | G168: Навоий_Дильноза опа | H168: PPS | I168: "Faxriddin-Farm Navoiy" Xk | J168: Эльфор р-р. для инф 5м/мл | K168: 30 | L168: 40621 | M168: 1218630 | N168: =+K168*15000 -> 450000 | O168: =+M168*$O$1 -> 219353.4 | P168: =+N168+O168 -> 669353.4 | Q168: 100 | R168: =+M168*Q168% -> 1218630 | S168: =M168-R168 -> 0
A169: 2025 | B169: 11 | C169: 45982 | D169: =+E169&G169 -> PPS00009933Навоий_Дильноза опа | E169: PPS00009933 | F169: Рано опа (Нав) | G169: Навоий_Дильноза опа | H169: PPS | I169: "Mubina Orzusi 2022" Mchj | J169: Эльфор р-р. для инф 5м/мл | K169: 50 | L169: 40621 | M169: 2031050 | N169: =+K169*15000 -> 750000 | O169: =+M169*$O$1 -> 365589 | P169: =+N169+O169 -> 1115589 | Q169: 100 | R169: =+M169*Q169% -> 2031050 | S169: =M169-R169 -> 0
A170: 2025 | B170: 11 | C170: 45985 | D170: =+E170&G170 -> PPS00009951Навоий_Дильноза опа | E170: PPS00009951 | F170: Рано опа (Нав) | G170: Навоий_Дильноза опа | H170: PPS | I170: "Grant Farm Plyus" Mchj | J170: Эльфор р-р. для инф 5м/мл | K170: 10 | L170: 40621 | M170: 406210 | N170: =+K170*15000 -> 150000 | O170: =+M170*$O$1 -> 73117.8 | P170: =+N170+O170 -> 223117.8 | Q170: 100 | R170: =+M170*Q170% -> 406210 | S170: =M170-R170 -> 0
A171: 2025 | B171: 11 | C171: 45985 | D171: =+E171&G171 -> PPS00009978Жиззах_Саодат опа | E171: PPS00009978 | F171: Дилноза опа (Жиз) | G171: Жиззах_Саодат опа | H171: PPS | I171: "Akobir Pharm 444" Mchj | J171: Эльфор р-р. для инф 5м/мл | K171: 50 | L171: 40621 | M171: 2031050 | N171: =+K171*15000 -> 750000 | O171: =+M171*$O$1 -> 365589 | P171: =+N171+O171 -> 1115589 | Q171: 100 | R171: =+M171*Q171% -> 2031050 | S171: =M171-R171 -> 0
A172: 2025 | B172: 11 | C172: 45985 | D172: =+E172&G172 -> PPS00009983Тошкент_Мохира опа | E172: PPS00009983 | F172: Нигора опа (Тош) | G172: Тошкент_Мохира опа | H172: PPS | I172: "Mmm-Apteka" Mchj | J172: Эльфор р-р. для инф 5м/мл | K172: 30 | L172: 40621 | M172: 1218630 | N172: =+K172*15000 -> 450000 | O172: =+M172*$O$1 -> 219353.4 | P172: =+N172+O172 -> 669353.4 | Q172: 100 | R172: =+M172*Q172% -> 1218630 | S172: =M172-R172 -> 0
A173: 2025 | B173: 11 | C173: 45985 | D173: =+E173&G173 -> PPS00009999Жиззах_Саодат опа | E173: PPS00009999 | F173: Дилноза опа (Жиз) | G173: Жиззах_Саодат опа | H173: PPS | I173: SUNISTAR FARM | J173: Эльфор р-р. для инф 5м/мл | K173: 50 | L173: 40621 | M173: 2031050 | N173: =+K173*15000 -> 750000 | O173: =+M173*$O$1 -> 365589 | P173: =+N173+O173 -> 1115589 | Q173: 100 | R173: =+M173*Q173% -> 2031050 | S173: =M173-R173 -> 0
A174: 2025 | B174: 11 | C174: 45985 | D174: =+E174&G174 -> PPS00010012Таш.Обл_Шахло опа | E174: PPS00010012 | F174: Шерзод ака (Т.О) | G174: Таш.Обл_Шахло опа | H174: PPS | I174: "111 Tabletok" Mchj | J174: Софин раствор для инфузий 5% 100 мл | K174: 20 | L174: 120000 | M174: 2400000 | N174: =+K174*35000 -> 700000 | O174: =+M174*$O$1 -> 432000 | P174: =+N174+O174 -> 1132000 | Q174: 100 | R174: =+M174*Q174% -> 2400000 | S174: =M174-R174 -> 0
A175: 2025 | B175: 11 | C175: 45985 | D175: =+E175&G175 -> PPS00010021Жиззах_Саодат опа | E175: PPS00010021 | F175: Жавлон ака (Жиз) | G175: Жиззах_Саодат опа | H175: PPS | I175: ООО "Zuhur Farm" | J175: Эльфор р-р. для инф 5м/мл | K175: 16 | L175: 40621 | M175: 649936 | N175: =+K175*15000 -> 240000 | O175: =+M175*$O$1 -> 116988.48 | P175: =+N175+O175 -> 356988.48 | Q175: 100 | R175: =+M175*Q175% -> 649936 | S175: =M175-R175 -> 0
A176: 2025 | B176: 11 | C176: 45985 | D176: =+E176&G176 -> PPS00010021Жиззах_Саодат опа | E176: PPS00010021 | F176: Жавлон ака (Жиз) | G176: Жиззах_Саодат опа | H176: PPS | I176: ООО "Zuhur Farm" | J176: Эльфор р-р. для инф 5м/мл | K176: 4 | L176: 36955.08 | M176: 147820.32 | N176: =+K176*15000 -> 60000 | O176: =+M176*$O$1 -> 26607.658 | P176: =+N176+O176 -> 86607.658 | Q176: 100 | R176: =+M176*Q176% -> 147820.32 | S176: =M176-R176 -> 0
A177: 2025 | B177: 11 | C177: 45985 | D177: =+E177&G177 -> PPS00010026Навоий_Дильноза опа | E177: PPS00010026 | F177: Рано опа (Нав) | G177: Навоий_Дильноза опа | H177: PPS | I177: "Navoiy Farm 999" Mchj | J177: Эльфор р-р. для инф 5м/мл | K177: 40 | L177: 40621 | M177: 1624840 | N177: =+K177*15000 -> 600000 | O177: =+M177*$O$1 -> 292471.2 | P177: =+N177+O177 -> 892471.2 | Q177: 100 | R177: =+M177*Q177% -> 1624840 | S177: =M177-R177 -> 0
A178: 2025 | B178: 11 | C178: 45986 | D178: =+E178&G178 -> PPS00010055Кашкадарьё_Феруз ака | E178: PPS00010055 | F178: Отабек ака (Шах) | G178: Кашкадарьё_Феруз ака | H178: PPS | I178: "Pharma Plus" Mchj | J178: Эпсол раствор для инфузий 12 мг/мл 50 мл | K178: 50 | L178: 65000 | M178: 3250000 | N178: =+K178*20000 -> 1000000 | O178: =+M178*$O$1 -> 585000 | P178: =+N178+O178 -> 1585000 | Q178: 100 | R178: =+M178*Q178% -> 3250000 | S178: =M178-R178 -> 0
A179: 2025 | B179: 12 | C179: 45992 | D179: =+E179&G179 -> PPS00010215Навоий_Дильноза опа | E179: PPS00010215 | F179: Рано опа (Нав) | G179: Навоий_Дильноза опа | H179: PPS | I179: "Navoiy Farm 999" Mchj | J179: Эльфор р-р. для инф 5м/мл | K179: 100 | L179: 40621 | M179: 4062100 | N179: =+K179*15000 -> 1500000 | O179: =+M179*$O$1 -> 731178 | P179: =+N179+O179 -> 2231178 | Q179: 100 | R179: =+M179*Q179% -> 4062100 | S179: =M179-R179 -> 0
A180: 2025 | B180: 12 | C180: 45992 | D180: =+E180&G180 -> PPS00010219Навоий_Дильноза опа | E180: PPS00010219 | F180: Рано опа (Нав) | G180: Навоий_Дильноза опа | H180: PPS | I180: "Azizjon Gulruxxon" Xk | J180: Эльфор р-р. для инф 5м/мл | K180: 20 | L180: 40621 | M180: 812420 | N180: =+K180*15000 -> 300000 | O180: =+M180*$O$1 -> 146235.6 | P180: =+N180+O180 -> 446235.6 | Q180: 100 | R180: =+M180*Q180% -> 812420 | S180: =M180-R180 -> 0
A181: 2025 | B181: 12 | C181: 45992 | D181: =+E181&G181 -> PPS00010228Сурхондарьё_Сарвар ака | E181: PPS00010228 | F181: Сарвар ака (Срх) | G181: Сурхондарьё_Сарвар ака | H181: PPS | I181: "ZAMIN-FARM-SIFAT" MChJ | J181: Эльфор р-р. для инф 5м/мл | K181: 60 | L181: 40621 | M181: 2437260 | N181: =+K181*15000 -> 900000 | O181: =+M181*$O$1 -> 438706.8 | P181: =+N181+O181 -> 1338706.8 | Q181: 100 | R181: =+M181*Q181% -> 2437260 | S181: =M181-R181 -> 0
A182: 2025 | B182: 12 | C182: 45993 | D182: =+E182&G182 -> PPS00010267Тошкент_Мохира опа | E182: PPS00010267 | F182: Лобархон опа (Тош) | G182: Тошкент_Мохира опа | H182: PPS | I182: "Biosfera Farm" Mchj | J182: Эльфор р-р. для инф 5м/мл | K182: 20 | L182: 40621 | M182: 812420 | N182: =+K182*15000 -> 300000 | O182: =+M182*$O$1 -> 146235.6 | P182: =+N182+O182 -> 446235.6 | Q182: 100 | R182: =+M182*Q182% -> 812420 | S182: =M182-R182 -> 0
A183: 2025 | B183: 12 | C183: 45994 | D183: =+E183&G183 -> PPS00010283Навоий_Дильноза опа | E183: PPS00010283 | F183: Дилноза опа (Нав) | G183: Навоий_Дильноза опа | H183: PPS | I183: "Grant Farm Plyus" Mchj | J183: Эльфор р-р. для инф 5м/мл | K183: 10 | L183: 40621 | M183: 406210 | N183: =+K183*15000 -> 150000 | O183: =+M183*$O$1 -> 73117.8 | P183: =+N183+O183 -> 223117.8 | Q183: 100 | R183: =+M183*Q183% -> 406210 | S183: =M183-R183 -> 0
A184: 2025 | B184: 12 | C184: 45994 | D184: =+E184&G184 -> PPS00010286Кашкадарьё_Феруз ака | E184: PPS00010286 | F184: Шахноза опа (Кшд) | G184: Кашкадарьё_Феруз ака | H184: PPS | I184: "Feru-Za Pharm" Xk | J184: Эпсол раствор для инфузий 12 мг/мл 50 мл | K184: 30 | L184: 65000 | M184: 1950000 | N184: =+K184*20000 -> 600000 | O184: =+M184*$O$1 -> 351000 | P184: =+N184+O184 -> 951000 | Q184: 100 | R184: =+M184*Q184% -> 1950000 | S184: =M184-R184 -> 0
A185: 2025 | B185: 12 | C185: 45995 | D185: =+E185&G185 -> PPS00010312Сурхондарьё_Сарвар ака | E185: PPS00010312 | F185: Сарвар ака (Срх) | G185: Сурхондарьё_Сарвар ака | H185: PPS | I185: "Doktor-Bek-Farm" Mchj | J185: Эльфор р-р. для инф 5м/мл | K185: 60 | L185: 40621 | M185: 2437260 | N185: =+K185*15000 -> 900000 | O185: =+M185*$O$1 -> 438706.8 | P185: =+N185+O185 -> 1338706.8 | Q185: 52 | R185: =+M185*Q185% -> 1267375.2 | S185: =M185-R185 -> 1169884.8
A186: 2025 | B186: 12 | C186: 45995 | D186: =+E186&G186 -> PPS00010303Тошкент_Мохира опа | E186: PPS00010303 | F186: Лобархон опа (Тош) | G186: Тошкент_Мохира опа | H186: PPS | I186: "Parus-Med-Farm" Mchj | J186: Эльфор р-р. для инф 5м/мл | K186: 10 | L186: 40621 | M186: 406210 | N186: =+K186*15000 -> 150000 | O186: =+M186*$O$1 -> 73117.8 | P186: =+N186+O186 -> 223117.8 | Q186: 100 | R186: =+M186*Q186% -> 406210 | S186: =M186-R186 -> 0
A187: 2025 | B187: 12 | C187: 45995 | D187: =+E187&G187 -> PPS00010325Навоий_Дильноза опа | E187: PPS00010325 | F187: Дилноза опа (Нав) | G187: Навоий_Дильноза опа | H187: PPS | I187: "FAYZ SADULLO" MChJ | J187: Эльфор р-р. для инф 5м/мл | K187: 20 | L187: 40621 | M187: 812420 | N187: =+K187*15000 -> 300000 | O187: =+M187*$O$1 -> 146235.6 | P187: =+N187+O187 -> 446235.6 | Q187: 100 | R187: =+M187*Q187% -> 812420 | S187: =M187-R187 -> 0
A188: 2025 | B188: 12 | C188: 45995 | D188: =+E188&G188 -> PPS00010329Навоий_Дильноза опа | E188: PPS00010329 | F188: Рано опа (Нав) | G188: Навоий_Дильноза опа | H188: PPS | I188: "Vita Pharm Navoiy" Mchj | J188: Эльфор р-р. для инф 5м/мл | K188: 20 | L188: 40621 | M188: 812420 | N188: =+K188*15000 -> 300000 | O188: =+M188*$O$1 -> 146235.6 | P188: =+N188+O188 -> 446235.6 | Q188: 100 | R188: =+M188*Q188% -> 812420 | S188: =M188-R188 -> 0
A189: 2025 | B189: 12 | C189: 45996 | D189: =+E189&G189 -> PPS00010343Кашкадарьё_Феруз ака | E189: PPS00010343 | F189: Отабек ака (Шах) | G189: Кашкадарьё_Феруз ака | H189: PPS | I189: "HOJAT-NUR-FARM" XK | J189: Эпсол раствор для инфузий 12 мг/мл 50 мл | K189: 10 | L189: 65000 | M189: 650000 | N189: =+K189*20000 -> 200000 | O189: =+M189*$O$1 -> 117000 | P189: =+N189+O189 -> 317000 | Q189: 100 | R189: =+M189*Q189% -> 650000 | S189: =M189-R189 -> 0
A190: 2025 | B190: 12 | C190: 45996 | D190: =+E190&G190 -> PPS00010354Бухоро_Рустам ака | E190: PPS00010354 | F190: Нозими опа (Бух) | G190: Бухоро_Рустам ака | H190: PPS | I190: "Al-Aziz Ayubhon" Mchj | J190: Эльфор р-р. для инф 5м/мл | K190: 50 | L190: 40621 | M190: 2031050 | N190: =+K190*15000 -> 750000 | O190: =+M190*$O$1 -> 365589 | P190: =+N190+O190 -> 1115589 | Q190: 100 | R190: =+M190*Q190% -> 2031050 | S190: =M190-R190 -> 0
A191: 2025 | B191: 12 | C191: 45996 | D191: =+E191&G191 -> PPS00010372Навоий_Дильноза опа | E191: PPS00010372 | F191: Рано опа (Нав) | G191: Навоий_Дильноза опа | H191: PPS | I191: "XUJAI-JAXON GRAND" MChJ | J191: Эльфор р-р. для инф 5м/мл | K191: 40 | L191: 40621 | M191: 1624840 | N191: =+K191*15000 -> 600000 | O191: =+M191*$O$1 -> 292471.2 | P191: =+N191+O191 -> 892471.2 | Q191: 100 | R191: =+M191*Q191% -> 1624840 | S191: =M191-R191 -> 0
A192: 2025 | B192: 12 | C192: 46000 | D192: =+E192&G192 -> PPS00010377Сурхондарьё_Сарвар ака | E192: PPS00010377 | F192: Сарвар ака (Срх) | G192: Сурхондарьё_Сарвар ака | H192: PPS | I192: "Fazliddin-Biznes" Xk | J192: Эльфор р-р. для инф 5м/мл | K192: 60 | L192: 40621 | M192: 2437260 | N192: =+K192*15000 -> 900000 | O192: =+M192*$O$1 -> 438706.8 | P192: =+N192+O192 -> 1338706.8 | Q192: 100 | R192: =+M192*Q192% -> 2437260 | S192: =M192-R192 -> 0
A193: 2025 | B193: 12 | C193: 46000 | D193: =+E193&G193 -> PPS00010384Жиззах_Саодат опа | E193: PPS00010384 | F193: Жавлон ака (Жиз) | G193: Жиззах_Саодат опа | H193: PPS | I193: ООО "Zuhur Farm" | J193: Эльфор р-р. для инф 5м/мл | K193: 48 | L193: 40621 | M193: 1949808 | N193: =+K193*15000 -> 720000 | O193: =+M193*$O$1 -> 350965.44 | P193: =+N193+O193 -> 1070965.4 | Q193: 100 | R193: =+M193*Q193% -> 1949808 | S193: =M193-R193 -> 0
A194: 2025 | B194: 12 | C194: 46000 | D194: =+E194&G194 -> PPS00010387Жиззах_Саодат опа | E194: PPS00010387 | F194: Дилноза опа (Жиз) | G194: Жиззах_Саодат опа | H194: PPS | I194: "Usta Maxmud"Xk | J194: Эльфор р-р. для инф 5м/мл | K194: 70 | L194: 40621 | M194: 2843470 | N194: =+K194*15000 -> 1050000 | O194: =+M194*$O$1 -> 511824.6 | P194: =+N194+O194 -> 1561824.6 | Q194: 100 | R194: =+M194*Q194% -> 2843470 | S194: =M194-R194 -> 0
A195: 2025 | B195: 12 | C195: 46000 | D195: =+E195&G195 -> PPS00010393Жиззах_Саодат опа | E195: PPS00010393 | F195: Дилноза опа (Жиз) | G195: Жиззах_Саодат опа | H195: PPS | I195: "Omad Sahovat Farm" Xk | J195: Эльфор р-р. для инф 5м/мл | K195: 20 | L195: 40621 | M195: 812420 | N195: =+K195*15000 -> 300000 | O195: =+M195*$O$1 -> 146235.6 | P195: =+N195+O195 -> 446235.6 | Q195: 100 | R195: =+M195*Q195% -> 812420 | S195: =M195-R195 -> 0
...

Sheet Перечеслени
A2: Названия строк | B2: Эльфор р-р. для инф 5м/мл | C2: Эпсол раствор для инфузий 12 мг/мл 50 мл | D2: Ландиос Раствор для инфузий 100мл стеклянные флаконы | E2: Софин раствор для инфузий 5% 100 мл | F2: Миранол раствор для инфузий 50 мл | G2: Итого
A3: Колва продажа итого Переч | B3: =SUMIFS('Продажа Переч'!$K:$K,'Продажа Переч'!$J:$J,B2) -> 29785 | C3: =SUMIFS('Продажа Переч'!$K:$K,'Продажа Переч'!$J:$J,C2) -> 9486 | D3: =SUMIFS('Продажа Переч'!$K:$K,'Продажа Переч'!$J:$J,D2) -> 5866 | E3: =SUMIFS('Продажа Переч'!$K:$K,'Продажа Переч'!$J:$J,E2) -> 5361 | F3: =SUMIFS('Продажа Переч'!$K:$K,'Продажа Переч'!$J:$J,F2) -> 12264
A4: Продажа Переч Сумма | B4: =SUMIFS('Продажа Переч'!$M:$M,'Продажа Переч'!$J:$J,B2) -> 1.1570641e+09 | C4: =SUMIFS('Продажа Переч'!$M:$M,'Продажа Переч'!$J:$J,C2) -> 613440000 | D4: =SUMIFS('Продажа Переч'!$M:$M,'Продажа Переч'!$J:$J,D2) -> 379530200 | E4: =SUMIFS('Продажа Переч'!$M:$M,'Продажа Переч'!$J:$J,E2) -> 641928000 | F4: =SUMIFS('Продажа Переч'!$M:$M,'Продажа Переч'!$J:$J,F2) -> 1100848000 | G4: =SUM(B4:F4) -> 3892810292
A5: Итого Расход инв И ЗП | B5: =SUMIFS('Продажа Переч'!$P:$P,'Продажа Переч'!$J:$J,B2) -> 6.115668e+08 | C5: =SUMIFS('Продажа Переч'!$P:$P,'Продажа Переч'!$J:$J,C2) -> 261816100 | D5: =SUMIFS('Продажа Переч'!$P:$P,'Продажа Переч'!$J:$J,D2) -> 154014456 | E5: =SUMIFS('Продажа Переч'!$P:$P,'Продажа Переч'!$J:$J,E2) -> 289030040 | F5: =SUMIFS('Продажа Переч'!$P:$P,'Продажа Переч'!$J:$J,F2) -> 393129800 | G5: =SUM(B5:F5) -> 1.7095572e+09
A6: Местные расходы | B6: =B4*$H$6 -> 1.1570641e+08 | C6: =C4*$H$6 -> 61344000 | D6: =D4*$H$6 -> 37953020 | E6: =E4*$H$6 -> 64192800 | F6: =F4*$H$6 -> 110084800 | G6: =SUM(B6:F6) -> 3.8928103e+08 | H6: 0.1
A7: Услуга Замин | B7: =(B16*B17)*$H$7 -> 49203405 | C7: =(C16*C17)*$H$7 -> 31200000 | D7: =(D16*D17)*$H$7 -> 23292000 | E7: =(E16*E17)*$H$7 -> 57600000 | F7: =(F16*F17)*$H$7 -> 32400000 | G7: =SUM(B7:F7) -> 1.936954e+08 | H7: 0.06
A8: Услуга Реф | B8: 7248399 | C8: 7248399 | D8: 7248399 | E8: 7248399 | F8: 7248399 | G8: =SUM(B8:F8) -> 36241995 | H8: 0.05
A9: Себестоимость | B9: =0.308*12000 -> 3696 | C9: 20000 | D9: 18000 | E9: 25000 | F9: 21000
A10: Сумма себеса | B10: =B9*B3 -> 110085360 | C10: =C9*C3 -> 189720000 | D10: =D9*D3 -> 105588000 | E10: =E9*E3 -> 134025000 | F10: =F9*F3 -> 257544000 | G10: =SUM(B10:F10) -> 796962360
A11: Прибыль | B11: =+B4-B5-B6-B7-B10 -> 2.7050212e+08 | C11: =+C4-C5-C6-C7-C10 -> 69359900 | D11: =+D4-D5-D6-D7-D10 -> 58682724 | E11: =+E4-E5-E6-E7-E10 -> 97080160 | F11: =+F4-F5-F6-F7-F10 -> 307689400 | G11: =SUM(B11:F11) -> 8.033143e+08
A12: Прибыль 50% PPS | B12: =+B11*$H$12 -> 1.3525106e+08 | C12: =+C11*$H$12 -> 34679950 | D12: =+D11*$H$12 -> 29341362 | E12: =+E11*$H$12 -> 48540080 | F12: =+F11*$H$12 -> 153844700 | G12: =SUM(B12:F12) -> 4.0165715e+08 | H12: 0.5
A13: Прибыль 50% Мурод ака | B13: =+B11*$H$13 -> 1.3525106e+08 | C13: =+C11*$H$13 -> 34679950 | D13: =+D11*$H$13 -> 29341362 | E13: =+E11*$H$13 -> 48540080 | F13: =+F11*$H$13 -> 153844700 | G13: =SUM(B13:F13) -> 4.0165715e+08 | H13: 0.5
A14: Поступления Переч | B14: =SUMIFS('Продажа Переч'!$R:$R,'Продажа Переч'!$J:$J,B2) -> 1.1362804e+09 | C14: =SUMIFS('Продажа Переч'!$R:$R,'Продажа Переч'!$J:$J,C2) -> 538673750 | D14: =SUMIFS('Продажа Переч'!$R:$R,'Продажа Переч'!$J:$J,D2) -> 284838515 | E14: =SUMIFS('Продажа Переч'!$R:$R,'Продажа Переч'!$J:$J,E2) -> 600378000 | F14: =SUMIFS('Продажа Переч'!$R:$R,'Продажа Переч'!$J:$J,F2) -> 927389200 | G14: =SUM(B14:F14) -> 3.4875598e+09
A15: Дебитор | B15: =SUMIFS('Продажа Переч'!$S:$S,'Продажа Переч'!$J:$J,B2) -> 20783712 | C15: =SUMIFS('Продажа Переч'!$S:$S,'Продажа Переч'!$J:$J,C2) -> 74766250 | D15: =SUMIFS('Продажа Переч'!$S:$S,'Продажа Переч'!$J:$J,D2) -> 94691685 | E15: =SUMIFS('Продажа Переч'!$S:$S,'Продажа Переч'!$J:$J,E2) -> 41550000 | F15: =SUMIFS('Продажа Переч'!$S:$S,'Продажа Переч'!$J:$J,F2) -> 173458800 | G15: =SUM(B15:F15) -> 4.0525045e+08
A16: Замин Приход колва | B16: 20188 | C16: 8000 | D16: 6000 | E16: 8000 | F16: 6000
B17: 40621 | C17: 65000 | D17: 64700 | E17: 120000 | F17: 90000
B18: =+B3-B16 -> 9597 | C18: =+C3-C16 -> 1486 | D18: =+D3-D16 -> -134 | E18: =+E3-E16 -> -2639 | F18: =+F3-F16 -> 6264 | G18: =+G3-G16 -> 0
B19: =+B18*B17 -> 389839737 | C19: =+C18*C17 -> 96590000 | D19: =+D18*D17 -> -8669800 | E19: =+E18*E17 -> -316680000 | F19: =+F18*F17 -> 563760000

Sheet 2H
A1: Названия строк | B1: Эльфор р-р. для инф 5м/мл | C1: Эпсол раствор для инфузий 12 мг/мл 50 мл | D1: Ландиос Раствор для инфузий 100мл стеклянные флаконы | E1: Софин раствор для инфузий 5% 100 мл | F1: Миранол раствор для инфузий 50 мл | G1: Итого
A2: Колва продажа итого 2В | B2: =SUMIFS('Продажа 2'!$J:$J,'Продажа 2'!$I:$I,B1) -> 71951 | C2: =SUMIFS('Продажа 2'!$J:$J,'Продажа 2'!$I:$I,C1) -> 10210 | D2: =SUMIFS('Продажа 2'!$J:$J,'Продажа 2'!$I:$I,D1) -> 11690 | E2: =SUMIFS('Продажа 2'!$J:$J,'Продажа 2'!$I:$I,E1) -> 11340 | F2: =SUMIFS('Продажа 2'!$J:$J,'Продажа 2'!$I:$I,F1) -> 14740
A3: Продажа сумма 2В | B3: =SUMIFS('Продажа 2'!$L:$L,'Продажа 2'!$I:$I,B1) -> 1236851700 | C3: =SUMIFS('Продажа 2'!$L:$L,'Продажа 2'!$I:$I,C1) -> 335410000 | D3: =SUMIFS('Продажа 2'!$L:$L,'Продажа 2'!$I:$I,D1) -> 361628000 | E3: =SUMIFS('Продажа 2'!$L:$L,'Продажа 2'!$I:$I,E1) -> 591916500 | F3: =SUMIFS('Продажа 2'!$L:$L,'Продажа 2'!$I:$I,F1) -> 587000000 | G3: =SUM(B3:F3) -> 3112806200
A4: Местные расходы | B4: =+B3*$H$4 -> 123685170 | C4: =+C3*$H$4 -> 33541000 | D4: =+D3*$H$4 -> 36162800 | E4: =+E3*$H$4 -> 59191650 | F4: =+F3*$H$4 -> 58700000 | G4: =SUM(B4:F4) -> 311280620 | H4: 0.1
A5: Услуга Замин | G5: =SUM(B5:F5) -> 0 | H5: 0.06
A6: Услуга Реф | G6: =SUM(B6:F6) -> 0 | H6: 0.05
A7: Себестоимость | B7: =0.308*12000 -> 3696 | C7: 20000 | D7: 18000 | E7: 25000 | F7: 21000
A8: Сумма себеса | B8: =B7*B2 -> 265930896 | C8: =C7*C2 -> 204200000 | D8: =D7*D2 -> 210420000 | E8: =E7*E2 -> 283500000 | F8: =F7*F2 -> 309540000 | G8: =SUM(B8:F8) -> 1273590896
A9: Прибыль | B9: =B3-B4-B5-B8 -> 847235634 | C9: =C3-C4-C5-C8 -> 97669000 | D9: =D3-D4-D5-D8 -> 115045200 | E9: =E3-E4-E5-E8 -> 249224850 | F9: =F3-F4-F5-F8 -> 218760000 | G9: =SUM(B9:F9) -> 1527934684
A10: Прибыль 50% PPS | B10: =B9*50% -> 423617817 | C10: =C9*50% -> 48834500 | D10: =D9*50% -> 57522600 | E10: =E9*50% -> 124612425 | F10: =F9*50% -> 109380000 | G10: =SUM(B10:F10) -> 763967342
A11: Прибыль 50% Мурод ака | B11: =+B9*50% -> 423617817 | C11: =+C9*50% -> 48834500 | D11: =+D9*50% -> 57522600 | E11: =+E9*50% -> 124612425 | F11: =+F9*50% -> 109380000 | G11: =SUM(B11:F11) -> 763967342
A12: Поступления кеш | B12: =SUMIFS('Продажа 2'!$N:$N,'Продажа 2'!$I:$I,B1) -> 1236721300 | C12: =SUMIFS('Продажа 2'!$N:$N,'Продажа 2'!$I:$I,C1) -> 263322200 | D12: =SUMIFS('Продажа 2'!$N:$N,'Продажа 2'!$I:$I,D1) -> 299287000 | E12: =SUMIFS('Продажа 2'!$N:$N,'Продажа 2'!$I:$I,E1) -> 512256500 | F12: =SUMIFS('Продажа 2'!$N:$N,'Продажа 2'!$I:$I,F1) -> 410256000 | G12: =SUM(B12:F12) -> 2721843000
A13: Дебитор | B13: =SUMIFS('Продажа 2'!$O:$O,'Продажа 2'!$I:$I,B1) -> 130400 | C13: =SUMIFS('Продажа 2'!$O:$O,'Продажа 2'!$I:$I,C1) -> 72087800 | D13: =SUMIFS('Продажа 2'!$O:$O,'Продажа 2'!$I:$I,D1) -> 62341000 | E13: =SUMIFS('Продажа 2'!$O:$O,'Продажа 2'!$I:$I,E1) -> 79660000 | F13: =SUMIFS('Продажа 2'!$O:$O,'Продажа 2'!$I:$I,F1) -> 176744000 | G13: =SUM(B13:F13) -> 390963200

Sheet Резюме
A1: Олпата Профи фарм
A2: Оплаты Итого | B2: =SUBTOTAL(9,B3:B8) -> 2510800664
A3: Кэш | B3: 300000000
A4: Профи | B4: 86123662
A5: Иброхим | B5: 165552675
A6: Сафора | B6: 172247327
A7: Рефликтив | B7: 1086877000
A8: Профи-Реф | B8: 700000000
A10: Сумма себеса | B10: =+'2H'!G8+Перечеслени!G10 -> 2070553256
A11: Прибыль | B11: ='2H'!G9+Перечеслени!G11 -> 2.331249e+09
A12: Прибыль 50% PPS | B12: =+B11/2 -> 1.1656245e+09
A13: Профи оплатил | B13: 2510800664
A14: Остаток сумма | B14: =B10+B11-B12-B13 -> 7.2537709e+08
A15: Дебитор Итого | B15: ='2H'!G13+Перечеслени!G15 -> 7.9621365e+08

Sheet Приход на Профи 
B1: Приход | H1: Продажа
B2: Epsol | C2: 45911 | D2: 0010825 | E2: 21604 | H2: 1 Epsol | I2: =8000+2000+1500+3000+1000+2000 -> 17500
B3: Epsol | C3: 46105 | D3: 0010126 | E3: 25822 | H3: 2 Epsol | I3: =2000+2000+1500+2000+2000+2000+2000+2000+1000 -> 16500
E4: =SUM(E2:E3) -> 47426 | H4: Итого | I4: =SUM(I2:I3) -> 34000
B7: Продажа
B8: 1 Elfor | C8: =2040+4080+4080 -> 10200
B9: 2 Elfor | C9: =7080+12000+12000+12000+12000+38040 -> 93120
B10: Итого | C10: =SUM(C8:C9) -> 103320
B11: Приход | G11: Продажа | J11: Возврат
B12: Miranol | C12: 45905 | D12: 0010825 | E12: 21906 | G12: 1 Miranol | H12: =6000+3000+1500+2000+6000+2500+3000+1000+2500 -> 27500 | J12: 0010825 | K12: 14319
B13: Miranol | C13: 46009 | D13: 0021025 | E13: 37000 | G13: 2 Miranol | H13: =3000+2000+1500+2200+3000+2000+2000+1000 -> 16700 | J13: 0010825 | K13: 1205
E14: =SUM(E12:E13) -> 58906 | G14: Итого | H14: =SUM(H12:H13) -> 44200 | J14: Итого | K14: =SUM(K12:K13) -> 15524 | L14: =+H14-K14 -> 28676
B17: Приход | H17: Продажа
B18: Sofin | C18: 45924 | D18: 0010825 | E18: 17690 | H18: 1 Sofin | I18: =8000+2000+1204+3000+2000+1000+2480 -> 19684
B19: Sofin | C19: 46088 | D19: 0010126 | E19: 16695 | H19: 2 Sofin | I19: =2695+4000+5000+2000+1000 -> 14695
E20: =SUM(E18:E19) -> 34385 | H20: Итого | I20: =SUM(I18:I19) -> 34379
B23: Приход | G23: Продажа
B24: Landios | C24: 45947 | D24: 0010825 | E24: 18264 | G24: 1 Landios | H24: =6000+2400+2000+3000 -> 13400
B25: Landios | C25: 45985 | D25: 0021125 | E25: 19771 | G25: 2 Landios | H25: =3000+2520+3000+2000+4000+2000+2000 -> 18520
B26: Landios | C26: 46149 | D26: 0010825 | E26: 19936 | G26: Итого | H26: =SUM(H24:H25) -> 31920
E27: =SUM(E24:E26) -> 57971
B39: Олпата Профи фарм
B40: Оплаты Итого | C40: =SUBTOTAL(9,C41:C46) -> 2510800664
B41: Кэш | C41: 300000000
B42: Профи | C42: 86123662
B43: Иброхим | C43: 165552675
B44: Сафора | C44: 172247327
B45: Рефликтив | C45: 1086877000
B46: Профи-Реф | C46: 700000000
B51: Названия строк | C51: Эльфор р-р. для инф 5м/мл | D51: Эпсол раствор для инфузий 12 мг/мл 50 мл | E51: Ландиос Раствор для инфузий 100мл стеклянные флаконы | F51: Софин раствор для инфузий 5% 100 мл | G51: Миранол раствор для инфузий 50 мл | H51: Итого | J51: завод | K51: 30000
B52: База цена | C52: 40621 | D52: 65000 | E52: 64700 | F52: 120000 | G52: 90000 | J52: продажа | K52: 50000
B53: Колва продажа итого Переч | C53: 29785 | D53: 9486 | E53: 5866 | F53: 5361 | G53: 12264 | K53: =+K52-K51 -> 20000
B54: Итого Расход инв И ЗП | C54: 611566799 | D54: 261816100 | E54: 154014456 | F54: 289030040 | G54: 393129800 | H54: =SUM(C54:G54) -> 1709557195 | J54: расход | K54: 10000
B55: Продажа Переч Сумма | C55: 1.1570641e+09 | D55: 613440000 | E55: 379530200 | F55: 641928000 | G55: 1100848000 | H55: =SUM(C55:G55) -> 3892810292 | J55: фойда | K55: =K53-K54 -> 10000
B56: Колва продажа итого 2В | C56: =77090-3700 -> 73390 | D56: 10210 | E56: 11690 | F56: 11335 | G56: 14740 | J56: оплата | K56: 35000 | L56: 50% Профи улуш
B57: Итого Продажа Перечес+2В | C57: =C56+C53 -> 103175 | D57: =D56+D53 -> 19696 | E57: =E56+E53 -> 17556 | F57: =F56+F53 -> 16696 | G57: =G56+G53 -> 27004
B58: Продажа сумма 2В | C58: 1236831000 | D58: 335410000 | E58: 361628000 | F58: 591916000 | G58: 587000000 | H58: =SUM(C58:G58) -> 3112785000
B59: Итого Продажа | C59: =C55+C58 -> 2393895092 | D59: =D55+D58 -> 948850000 | E59: =E55+E58 -> 741158200 | F59: =F55+F58 -> 1233844000 | G59: =G55+G58 -> 1687848000 | H59: =SUM(C59:G59) -> 7005595292
B60: Местные расходы | C60: =+C59*$I$60 -> 2.3938951e+08 | D60: =+D59*$I$60 -> 94885000 | E60: =+E59*$I$60 -> 74115820 | F60: =+F59*$I$60 -> 123384400 | G60: =+G59*$I$60 -> 168784800 | H60: =SUM(C60:G60) -> 7.0055953e+08 | I60: 0.1
B61: Услуга Замин | C61: =+C71*6% -> 49203405 | D61: =+D71*6% -> 31200000 | E61: =+E71*6% -> 23292000 | F61: =+F71*6% -> 57600000 | G61: =+G71*6% -> 32400000 | H61: =SUM(C61:G61) -> 1.936954e+08 | I61: 0.06 | J61: Сумма себеса | K61: 2075746800
B62: Услуга Реф | C62: =+C55*$I$62 -> 57853205 | D62: =+D55*$I$62 -> 30672000 | E62: =+E55*$I$62 -> 18976510 | F62: =+F55*$I$62 -> 32096400 | H62: =SUM(C62:G62) -> 1.3959811e+08 | I62: 0.05 | J62: Прибыль | K62: 2.1313958e+09
B63: Себестоимость | C63: =0.308*12000 -> 3696 | D63: 20000 | E63: 18000 | F63: 25000 | G63: 21000 | J63: Прибыль 50% PPS | K63: 1.0656979e+09
B64: Сумма себеса | C64: =C57*C63 -> 381334800 | D64: =D57*D63 -> 393920000 | E64: =E57*E63 -> 316008000 | F64: =F57*F63 -> 417400000 | G64: =G57*G63 -> 567084000 | H64: =SUM(C64:G64) -> 2075746800 | J64: Профи оплатил | K64: 2510800664
B65: Прибыль | C65: =C59-C54-C60-C61-C62-C64 -> 1.0545474e+09 | D65: =D59-D54-D60-D61-D62-D64 -> 136356900 | E65: =E59-E54-E60-E61-E62-E64 -> 154751414 | F65: =F59-F54-F60-F61-F62-F64 -> 314333160 | G65: =G59-G54-G60-G61-G62-G64 -> #VALUE! | H65: =SUM(C65:G65) -> #VALUE! | J65: Остаток сумма | K65: =K61+K62-K63-K64 -> 6.3064406e+08
B66: Прибыль 50% PPS | C66: =+C65*$I$66 -> 5.2727369e+08 | D66: =+D65*$I$66 -> 68178450 | E66: =+E65*$I$66 -> 77375707 | F66: =+F65*$I$66 -> 157166580 | G66: =+G65*$I$66 -> #VALUE! | H66: =SUM(C66:G66) -> #VALUE! | I66: 0.5
B67: Прибыль 50% Мурод ака | C67: =C65*$I$67 -> 5.2727369e+08 | D67: =D65*$I$67 -> 68178450 | E67: =E65*$I$67 -> 77375707 | F67: =F65*$I$67 -> 157166580 | G67: =G65*$I$67 -> #VALUE! | H67: =SUM(C67:G67) -> #VALUE! | I67: 0.5
B68: Профи оплатил | C68: =$C$40/5 -> 5.0216013e+08 | D68: =$C$40/5 -> 5.0216013e+08 | E68: =$C$40/5 -> 5.0216013e+08 | F68: =$C$40/5 -> 5.0216013e+08 | G68: =$C$40/5 -> 5.0216013e+08 | H68: =SUM(C68:G68) -> 2510800664
B69: Остаток сумма | C69: =C6 -> 0 | H69: =H64+H65-H68-H66 -> #VALUE!
B70: Замин приход колва | C70: 20188 | D70: 8000 | E70: 6000 | F70: 8000 | G70: 6000
C71: =C70*C52 -> 820056748 | D71: =+D52*D70 -> 520000000 | E71: =+E52*E70 -> 388200000 | F71: =+F52*F70 -> 960000000 | G71: =+G52*G70 -> 540000000
